{
    "Meta Data": {
        "1. Information": "Daily Time Series with Splits and Dividend Events",
        "2. Symbol": "BDXA",
        "3. Last Refreshed": "2017-12-01",
        "4. Output Size": "Full size",
        "5. Time Zone": "US/Eastern"
    },
    "Time Series (Daily)": {
        "2017-12-01": {
            "1. open": "60.8400",
            "2. high": "61.3400",
            "3. low": "60.0400",
            "4. close": "60.5000",
            "5. adjusted close": "60.5000",
            "6. volume": "115175",
            "7. dividend amount": "0.0000",
            "8. split coefficient": "1.0000"
        },
        "2017-11-30": {
            "1. open": "60.5300",
            "2. high": "60.7500",
            "3. low": "59.9000",
            "4. close": "60.6800",
            "5. adjusted close": "60.6800",
            "6. volume": "139677",
            "7. dividend amount": "0.0000",
            "8. split coefficient": "1.0000"
        },
        "2017-11-29": {
            "1. open": "60.2300",
            "2. high": "60.4500",
            "3. low": "60.1000",
            "4. close": "60.4000",
            "5. adjusted close": "60.4000",
            "6. volume": "66119",
            "7. dividend amount": "0.0000",
            "8. split coefficient": "1.0000"
        },
        "2017-11-28": {
            "1. open": "60.3300",
            "2. high": "60.5200",
            "3. low": "59.4000",
            "4. close": "60.4100",
            "5. adjusted close": "60.4100",
            "6. volume": "268701",
            "7. dividend amount": "0.0000",
            "8. split coefficient": "1.0000"
        },
        "2017-11-27": {
            "1. open": "60.3200",
            "2. high": "61.8400",
            "3. low": "59.9000",
            "4. close": "60.1700",
            "5. adjusted close": "60.1700",
            "6. volume": "131092",
            "7. dividend amount": "0.0000",
            "8. split coefficient": "1.0000"
        },
        "2017-11-24": {
            "1. open": "59.5400",
            "2. high": "60.2300",
            "3. low": "59.5400",
            "4. close": "60.2300",
            "5. adjusted close": "60.2300",
            "6. volume": "3049",
            "7. dividend amount": "0.0000",
            "8. split coefficient": "1.0000"
        },
        "2017-11-22": {
            "1. open": "60.1700",
            "2. high": "60.2500",
            "3. low": "59.5400",
            "4. close": "59.7500",
            "5. adjusted close": "59.7500",
            "6. volume": "20612",
            "7. dividend amount": "0.0000",
            "8. split coefficient": "1.0000"
        },
        "2017-11-21": {
            "1. open": "59.3200",
            "2. high": "60.4600",
            "3. low": "59.3200",
            "4. close": "60.3100",
            "5. adjusted close": "60.3100",
            "6. volume": "180611",
            "7. dividend amount": "0.0000",
            "8. split coefficient": "1.0000"
        },
        "2017-11-20": {
            "1. open": "58.9300",
            "2. high": "59.5100",
            "3. low": "58.9300",
            "4. close": "59.2700",
            "5. adjusted close": "59.2700",
            "6. volume": "70542",
            "7. dividend amount": "0.0000",
            "8. split coefficient": "1.0000"
        },
        "2017-11-17": {
            "1. open": "59.2600",
            "2. high": "59.6900",
            "3. low": "58.9000",
            "4. close": "59.1000",
            "5. adjusted close": "59.1000",
            "6. volume": "65764",
            "7. dividend amount": "0.0000",
            "8. split coefficient": "1.0000"
        },
        "2017-11-16": {
            "1. open": "58.7900",
            "2. high": "59.3400",
            "3. low": "58.7900",
            "4. close": "59.1200",
            "5. adjusted close": "59.1200",
            "6. volume": "238062",
            "7. dividend amount": "0.0000",
            "8. split coefficient": "1.0000"
        },
        "2017-11-15": {
            "1. open": "58.7200",
            "2. high": "59.1400",
            "3. low": "58.7100",
            "4. close": "58.8200",
            "5. adjusted close": "58.8200",
            "6. volume": "161047",
            "7. dividend amount": "0.0000",
            "8. split coefficient": "1.0000"
        },
        "2017-11-14": {
            "1. open": "58.9700",
            "2. high": "59.3000",
            "3. low": "58.7800",
            "4. close": "59.1700",
            "5. adjusted close": "59.1700",
            "6. volume": "319093",
            "7. dividend amount": "0.0000",
            "8. split coefficient": "1.0000"
        },
        "2017-11-13": {
            "1. open": "58.3900",
            "2. high": "58.9200",
            "3. low": "58.3300",
            "4. close": "58.8700",
            "5. adjusted close": "58.8700",
            "6. volume": "217809",
            "7. dividend amount": "0.0000",
            "8. split coefficient": "1.0000"
        },
        "2017-11-10": {
            "1. open": "59.5800",
            "2. high": "59.5800",
            "3. low": "58.1250",
            "4. close": "58.5900",
            "5. adjusted close": "58.5900",
            "6. volume": "259296",
            "7. dividend amount": "0.0000",
            "8. split coefficient": "1.0000"
        },
        "2017-11-09": {
            "1. open": "59.3300",
            "2. high": "59.8400",
            "3. low": "59.1500",
            "4. close": "59.6600",
            "5. adjusted close": "59.6600",
            "6. volume": "257559",
            "7. dividend amount": "0.0000",
            "8. split coefficient": "1.0000"
        },
        "2017-11-08": {
            "1. open": "59.3100",
            "2. high": "59.6100",
            "3. low": "58.9500",
            "4. close": "59.2800",
            "5. adjusted close": "59.2800",
            "6. volume": "73903",
            "7. dividend amount": "0.0000",
            "8. split coefficient": "1.0000"
        },
        "2017-11-07": {
            "1. open": "59.6400",
            "2. high": "59.6800",
            "3. low": "58.8200",
            "4. close": "59.1900",
            "5. adjusted close": "59.1900",
            "6. volume": "428236",
            "7. dividend amount": "0.0000",
            "8. split coefficient": "1.0000"
        },
        "2017-11-06": {
            "1. open": "59.9300",
            "2. high": "59.9300",
            "3. low": "59.2000",
            "4. close": "59.2400",
            "5. adjusted close": "59.2400",
            "6. volume": "22944",
            "7. dividend amount": "0.0000",
            "8. split coefficient": "1.0000"
        },
        "2017-11-03": {
            "1. open": "59.0000",
            "2. high": "59.8150",
            "3. low": "58.7700",
            "4. close": "59.7200",
            "5. adjusted close": "59.7200",
            "6. volume": "132942",
            "7. dividend amount": "0.0000",
            "8. split coefficient": "1.0000"
        },
        "2017-11-02": {
            "1. open": "57.4500",
            "2. high": "59.8800",
            "3. low": "57.2100",
            "4. close": "59.7000",
            "5. adjusted close": "59.7000",
            "6. volume": "287859",
            "7. dividend amount": "0.0000",
            "8. split coefficient": "1.0000"
        },
        "2017-11-01": {
            "1. open": "56.0800",
            "2. high": "57.0200",
            "3. low": "56.0800",
            "4. close": "56.5700",
            "5. adjusted close": "56.5700",
            "6. volume": "144243",
            "7. dividend amount": "0.0000",
            "8. split coefficient": "1.0000"
        },
        "2017-10-31": {
            "1. open": "56.4500",
            "2. high": "56.8460",
            "3. low": "56.4500",
            "4. close": "56.7900",
            "5. adjusted close": "56.7900",
            "6. volume": "435311",
            "7. dividend amount": "0.0000",
            "8. split coefficient": "1.0000"
        },
        "2017-10-30": {
            "1. open": "56.8800",
            "2. high": "57.0800",
            "3. low": "56.6100",
            "4. close": "56.7400",
            "5. adjusted close": "56.7400",
            "6. volume": "358649",
            "7. dividend amount": "0.0000",
            "8. split coefficient": "1.0000"
        },
        "2017-10-27": {
            "1. open": "57.2600",
            "2. high": "57.2600",
            "3. low": "56.8500",
            "4. close": "57.0900",
            "5. adjusted close": "57.0900",
            "6. volume": "86199",
            "7. dividend amount": "0.0000",
            "8. split coefficient": "1.0000"
        },
        "2017-10-26": {
            "1. open": "57.0500",
            "2. high": "57.5500",
            "3. low": "56.8750",
            "4. close": "57.1800",
            "5. adjusted close": "57.1800",
            "6. volume": "89647",
            "7. dividend amount": "0.0000",
            "8. split coefficient": "1.0000"
        },
        "2017-10-25": {
            "1. open": "57.4800",
            "2. high": "57.4800",
            "3. low": "57.0300",
            "4. close": "57.0500",
            "5. adjusted close": "57.0500",
            "6. volume": "130217",
            "7. dividend amount": "0.0000",
            "8. split coefficient": "1.0000"
        },
        "2017-10-24": {
            "1. open": "57.3300",
            "2. high": "57.3300",
            "3. low": "56.8840",
            "4. close": "57.2000",
            "5. adjusted close": "57.2000",
            "6. volume": "177425",
            "7. dividend amount": "0.0000",
            "8. split coefficient": "1.0000"
        },
        "2017-10-23": {
            "1. open": "57.7400",
            "2. high": "57.7900",
            "3. low": "57.0980",
            "4. close": "57.1300",
            "5. adjusted close": "57.1300",
            "6. volume": "139737",
            "7. dividend amount": "0.0000",
            "8. split coefficient": "1.0000"
        },
        "2017-10-20": {
            "1. open": "56.8400",
            "2. high": "57.5600",
            "3. low": "56.7500",
            "4. close": "57.5600",
            "5. adjusted close": "57.5600",
            "6. volume": "163483",
            "7. dividend amount": "0.0000",
            "8. split coefficient": "1.0000"
        },
        "2017-10-19": {
            "1. open": "56.4200",
            "2. high": "56.7500",
            "3. low": "56.2870",
            "4. close": "56.7100",
            "5. adjusted close": "56.7100",
            "6. volume": "16740",
            "7. dividend amount": "0.0000",
            "8. split coefficient": "1.0000"
        },
        "2017-10-18": {
            "1. open": "55.7800",
            "2. high": "56.4300",
            "3. low": "55.7200",
            "4. close": "56.4300",
            "5. adjusted close": "56.4300",
            "6. volume": "180948",
            "7. dividend amount": "0.0000",
            "8. split coefficient": "1.0000"
        },
        "2017-10-17": {
            "1. open": "55.2600",
            "2. high": "55.6570",
            "3. low": "55.2500",
            "4. close": "55.5400",
            "5. adjusted close": "55.5400",
            "6. volume": "20875",
            "7. dividend amount": "0.0000",
            "8. split coefficient": "1.0000"
        },
        "2017-10-16": {
            "1. open": "55.2100",
            "2. high": "55.2950",
            "3. low": "54.8300",
            "4. close": "55.2400",
            "5. adjusted close": "55.2400",
            "6. volume": "15238",
            "7. dividend amount": "0.0000",
            "8. split coefficient": "1.0000"
        },
        "2017-10-13": {
            "1. open": "54.8400",
            "2. high": "55.2600",
            "3. low": "54.5300",
            "4. close": "55.2600",
            "5. adjusted close": "55.2600",
            "6. volume": "197744",
            "7. dividend amount": "0.0000",
            "8. split coefficient": "1.0000"
        },
        "2017-10-12": {
            "1. open": "54.4900",
            "2. high": "54.8500",
            "3. low": "54.4900",
            "4. close": "54.8000",
            "5. adjusted close": "54.8000",
            "6. volume": "375135",
            "7. dividend amount": "0.7656",
            "8. split coefficient": "1.0000"
        },
        "2017-10-11": {
            "1. open": "55.3300",
            "2. high": "55.3300",
            "3. low": "55.0700",
            "4. close": "55.2600",
            "5. adjusted close": "54.4986",
            "6. volume": "138699",
            "7. dividend amount": "0.0000",
            "8. split coefficient": "1.0000"
        },
        "2017-10-10": {
            "1. open": "55.3000",
            "2. high": "55.3000",
            "3. low": "54.9000",
            "4. close": "55.0700",
            "5. adjusted close": "54.3112",
            "6. volume": "184035",
            "7. dividend amount": "0.0000",
            "8. split coefficient": "1.0000"
        },
        "2017-10-09": {
            "1. open": "55.1900",
            "2. high": "55.2150",
            "3. low": "55.0200",
            "4. close": "55.1700",
            "5. adjusted close": "54.4099",
            "6. volume": "290583",
            "7. dividend amount": "0.0000",
            "8. split coefficient": "1.0000"
        },
        "2017-10-06": {
            "1. open": "55.0300",
            "2. high": "55.3400",
            "3. low": "55.0300",
            "4. close": "55.3200",
            "5. adjusted close": "54.5578",
            "6. volume": "225496",
            "7. dividend amount": "0.0000",
            "8. split coefficient": "1.0000"
        },
        "2017-10-05": {
            "1. open": "54.7900",
            "2. high": "55.1500",
            "3. low": "54.7470",
            "4. close": "55.1500",
            "5. adjusted close": "54.3901",
            "6. volume": "93620",
            "7. dividend amount": "0.0000",
            "8. split coefficient": "1.0000"
        },
        "2017-10-04": {
            "1. open": "54.7900",
            "2. high": "54.8600",
            "3. low": "54.7210",
            "4. close": "54.8000",
            "5. adjusted close": "54.0449",
            "6. volume": "37653",
            "7. dividend amount": "0.0000",
            "8. split coefficient": "1.0000"
        },
        "2017-10-03": {
            "1. open": "55.1500",
            "2. high": "55.1500",
            "3. low": "54.4900",
            "4. close": "54.5400",
            "5. adjusted close": "53.7885",
            "6. volume": "353049",
            "7. dividend amount": "0.0000",
            "8. split coefficient": "1.0000"
        },
        "2017-10-02": {
            "1. open": "55.3100",
            "2. high": "55.3100",
            "3. low": "54.9600",
            "4. close": "54.9900",
            "5. adjusted close": "54.2323",
            "6. volume": "366936",
            "7. dividend amount": "0.0000",
            "8. split coefficient": "1.0000"
        },
        "2017-09-29": {
            "1. open": "54.5500",
            "2. high": "55.2600",
            "3. low": "54.5350",
            "4. close": "55.2600",
            "5. adjusted close": "54.4986",
            "6. volume": "726639",
            "7. dividend amount": "0.0000",
            "8. split coefficient": "1.0000"
        },
        "2017-09-28": {
            "1. open": "54.4800",
            "2. high": "54.7190",
            "3. low": "54.4200",
            "4. close": "54.5700",
            "5. adjusted close": "53.8181",
            "6. volume": "303020",
            "7. dividend amount": "0.0000",
            "8. split coefficient": "1.0000"
        },
        "2017-09-27": {
            "1. open": "54.8100",
            "2. high": "54.8100",
            "3. low": "54.3700",
            "4. close": "54.5400",
            "5. adjusted close": "53.7885",
            "6. volume": "480924",
            "7. dividend amount": "0.0000",
            "8. split coefficient": "1.0000"
        },
        "2017-09-26": {
            "1. open": "54.6790",
            "2. high": "54.7400",
            "3. low": "54.4600",
            "4. close": "54.7400",
            "5. adjusted close": "53.9858",
            "6. volume": "105971",
            "7. dividend amount": "0.0000",
            "8. split coefficient": "1.0000"
        },
        "2017-09-25": {
            "1. open": "54.5000",
            "2. high": "54.6100",
            "3. low": "54.3100",
            "4. close": "54.4700",
            "5. adjusted close": "53.7195",
            "6. volume": "296593",
            "7. dividend amount": "0.0000",
            "8. split coefficient": "1.0000"
        },
        "2017-09-22": {
            "1. open": "54.4100",
            "2. high": "55.0900",
            "3. low": "54.2500",
            "4. close": "54.5700",
            "5. adjusted close": "53.8181",
            "6. volume": "880997",
            "7. dividend amount": "0.0000",
            "8. split coefficient": "1.0000"
        },
        "2017-09-21": {
            "1. open": "54.6000",
            "2. high": "54.6600",
            "3. low": "54.1800",
            "4. close": "54.2400",
            "5. adjusted close": "53.4927",
            "6. volume": "57026",
            "7. dividend amount": "0.0000",
            "8. split coefficient": "1.0000"
        },
        "2017-09-20": {
            "1. open": "54.6100",
            "2. high": "54.7400",
            "3. low": "54.3710",
            "4. close": "54.7000",
            "5. adjusted close": "53.9463",
            "6. volume": "804133",
            "7. dividend amount": "0.0000",
            "8. split coefficient": "1.0000"
        },
        "2017-09-19": {
            "1. open": "55.1000",
            "2. high": "55.1000",
            "3. low": "54.4000",
            "4. close": "54.5400",
            "5. adjusted close": "53.7885",
            "6. volume": "1087742",
            "7. dividend amount": "0.0000",
            "8. split coefficient": "1.0000"
        },
        "2017-09-18": {
            "1. open": "55.1500",
            "2. high": "56.6500",
            "3. low": "54.9900",
            "4. close": "55.0100",
            "5. adjusted close": "54.2521",
            "6. volume": "328287",
            "7. dividend amount": "0.0000",
            "8. split coefficient": "1.0000"
        },
        "2017-09-15": {
            "1. open": "55.1900",
            "2. high": "55.4100",
            "3. low": "54.9000",
            "4. close": "55.0000",
            "5. adjusted close": "54.2422",
            "6. volume": "309998",
            "7. dividend amount": "0.0000",
            "8. split coefficient": "1.0000"
        },
        "2017-09-14": {
            "1. open": "55.2700",
            "2. high": "55.4800",
            "3. low": "55.1200",
            "4. close": "55.4600",
            "5. adjusted close": "54.6959",
            "6. volume": "111556",
            "7. dividend amount": "0.0000",
            "8. split coefficient": "1.0000"
        },
        "2017-09-13": {
            "1. open": "55.9300",
            "2. high": "55.9300",
            "3. low": "55.0700",
            "4. close": "55.2500",
            "5. adjusted close": "54.4887",
            "6. volume": "236735",
            "7. dividend amount": "0.0000",
            "8. split coefficient": "1.0000"
        },
        "2017-09-12": {
            "1. open": "56.2060",
            "2. high": "56.3890",
            "3. low": "56.0840",
            "4. close": "56.2300",
            "5. adjusted close": "55.4552",
            "6. volume": "144882",
            "7. dividend amount": "0.0000",
            "8. split coefficient": "1.0000"
        },
        "2017-09-11": {
            "1. open": "56.5800",
            "2. high": "56.7100",
            "3. low": "56.3600",
            "4. close": "56.4600",
            "5. adjusted close": "55.6821",
            "6. volume": "17457",
            "7. dividend amount": "0.0000",
            "8. split coefficient": "1.0000"
        },
        "2017-09-08": {
            "1. open": "55.7200",
            "2. high": "56.6000",
            "3. low": "55.7200",
            "4. close": "56.5600",
            "5. adjusted close": "55.7807",
            "6. volume": "130198",
            "7. dividend amount": "0.0000",
            "8. split coefficient": "1.0000"
        },
        "2017-09-07": {
            "1. open": "55.6600",
            "2. high": "55.9120",
            "3. low": "55.6500",
            "4. close": "55.6600",
            "5. adjusted close": "54.8931",
            "6. volume": "246096",
            "7. dividend amount": "0.0000",
            "8. split coefficient": "1.0000"
        },
        "2017-09-06": {
            "1. open": "55.7900",
            "2. high": "55.7900",
            "3. low": "55.5400",
            "4. close": "55.6000",
            "5. adjusted close": "54.8339",
            "6. volume": "212283",
            "7. dividend amount": "0.0000",
            "8. split coefficient": "1.0000"
        },
        "2017-09-05": {
            "1. open": "55.5500",
            "2. high": "55.8500",
            "3. low": "55.2600",
            "4. close": "55.8300",
            "5. adjusted close": "55.0608",
            "6. volume": "129689",
            "7. dividend amount": "0.0000",
            "8. split coefficient": "1.0000"
        },
        "2017-09-01": {
            "1. open": "55.6200",
            "2. high": "55.6200",
            "3. low": "55.2920",
            "4. close": "55.5900",
            "5. adjusted close": "54.8241",
            "6. volume": "95533",
            "7. dividend amount": "0.0000",
            "8. split coefficient": "1.0000"
        },
        "2017-08-31": {
            "1. open": "55.4900",
            "2. high": "55.6500",
            "3. low": "55.2410",
            "4. close": "55.6200",
            "5. adjusted close": "54.8537",
            "6. volume": "117600",
            "7. dividend amount": "0.0000",
            "8. split coefficient": "1.0000"
        },
        "2017-08-30": {
            "1. open": "55.5700",
            "2. high": "55.5700",
            "3. low": "55.1800",
            "4. close": "55.2400",
            "5. adjusted close": "54.4789",
            "6. volume": "237462",
            "7. dividend amount": "0.0000",
            "8. split coefficient": "1.0000"
        },
        "2017-08-29": {
            "1. open": "55.4000",
            "2. high": "55.5400",
            "3. low": "55.2600",
            "4. close": "55.4600",
            "5. adjusted close": "54.6959",
            "6. volume": "125011",
            "7. dividend amount": "0.0000",
            "8. split coefficient": "1.0000"
        },
        "2017-08-28": {
            "1. open": "55.4710",
            "2. high": "55.5500",
            "3. low": "55.4320",
            "4. close": "55.5500",
            "5. adjusted close": "54.7846",
            "6. volume": "18641",
            "7. dividend amount": "0.0000",
            "8. split coefficient": "1.0000"
        },
        "2017-08-25": {
            "1. open": "55.2700",
            "2. high": "55.4200",
            "3. low": "55.2700",
            "4. close": "55.2800",
            "5. adjusted close": "54.5183",
            "6. volume": "39371",
            "7. dividend amount": "0.0000",
            "8. split coefficient": "1.0000"
        },
        "2017-08-24": {
            "1. open": "55.5400",
            "2. high": "55.5400",
            "3. low": "55.0600",
            "4. close": "55.1600",
            "5. adjusted close": "54.4000",
            "6. volume": "58202",
            "7. dividend amount": "0.0000",
            "8. split coefficient": "1.0000"
        },
        "2017-08-23": {
            "1. open": "55.5100",
            "2. high": "55.5100",
            "3. low": "55.0900",
            "4. close": "55.2800",
            "5. adjusted close": "54.5183",
            "6. volume": "190465",
            "7. dividend amount": "0.0000",
            "8. split coefficient": "1.0000"
        },
        "2017-08-22": {
            "1. open": "55.5200",
            "2. high": "55.7900",
            "3. low": "55.5200",
            "4. close": "55.7400",
            "5. adjusted close": "54.9720",
            "6. volume": "354632",
            "7. dividend amount": "0.0000",
            "8. split coefficient": "1.0000"
        },
        "2017-08-21": {
            "1. open": "55.3200",
            "2. high": "55.5300",
            "3. low": "55.0200",
            "4. close": "55.3700",
            "5. adjusted close": "54.6071",
            "6. volume": "127233",
            "7. dividend amount": "0.0000",
            "8. split coefficient": "1.0000"
        },
        "2017-08-18": {
            "1. open": "55.2800",
            "2. high": "55.3800",
            "3. low": "54.9000",
            "4. close": "55.2300",
            "5. adjusted close": "54.4690",
            "6. volume": "275036",
            "7. dividend amount": "0.0000",
            "8. split coefficient": "1.0000"
        },
        "2017-08-17": {
            "1. open": "55.7810",
            "2. high": "55.9800",
            "3. low": "55.3800",
            "4. close": "55.3800",
            "5. adjusted close": "54.6170",
            "6. volume": "77961",
            "7. dividend amount": "0.0000",
            "8. split coefficient": "1.0000"
        },
        "2017-08-16": {
            "1. open": "55.7000",
            "2. high": "56.0500",
            "3. low": "55.7000",
            "4. close": "55.7400",
            "5. adjusted close": "54.9720",
            "6. volume": "216576",
            "7. dividend amount": "0.0000",
            "8. split coefficient": "1.0000"
        },
        "2017-08-15": {
            "1. open": "55.8500",
            "2. high": "56.0860",
            "3. low": "55.6700",
            "4. close": "55.6700",
            "5. adjusted close": "54.9030",
            "6. volume": "414514",
            "7. dividend amount": "0.0000",
            "8. split coefficient": "1.0000"
        },
        "2017-08-14": {
            "1. open": "55.5400",
            "2. high": "57.2100",
            "3. low": "55.5050",
            "4. close": "55.8600",
            "5. adjusted close": "55.0903",
            "6. volume": "939404",
            "7. dividend amount": "0.0000",
            "8. split coefficient": "1.0000"
        },
        "2017-08-11": {
            "1. open": "55.4700",
            "2. high": "55.9300",
            "3. low": "55.3000",
            "4. close": "55.7500",
            "5. adjusted close": "54.9819",
            "6. volume": "61971",
            "7. dividend amount": "0.0000",
            "8. split coefficient": "1.0000"
        },
        "2017-08-10": {
            "1. open": "55.1800",
            "2. high": "55.5290",
            "3. low": "55.1800",
            "4. close": "55.2900",
            "5. adjusted close": "54.5282",
            "6. volume": "224417",
            "7. dividend amount": "0.0000",
            "8. split coefficient": "1.0000"
        },
        "2017-08-09": {
            "1. open": "54.9900",
            "2. high": "55.3200",
            "3. low": "54.9900",
            "4. close": "55.2100",
            "5. adjusted close": "54.4493",
            "6. volume": "99505",
            "7. dividend amount": "0.0000",
            "8. split coefficient": "1.0000"
        },
        "2017-08-08": {
            "1. open": "55.7800",
            "2. high": "55.7800",
            "3. low": "55.1000",
            "4. close": "55.1100",
            "5. adjusted close": "54.3507",
            "6. volume": "93154",
            "7. dividend amount": "0.0000",
            "8. split coefficient": "1.0000"
        },
        "2017-08-07": {
            "1. open": "55.0900",
            "2. high": "55.4600",
            "3. low": "55.0500",
            "4. close": "55.4000",
            "5. adjusted close": "54.6367",
            "6. volume": "54231",
            "7. dividend amount": "0.0000",
            "8. split coefficient": "1.0000"
        },
        "2017-08-04": {
            "1. open": "55.6900",
            "2. high": "55.7800",
            "3. low": "54.9100",
            "4. close": "55.2300",
            "5. adjusted close": "54.4690",
            "6. volume": "404173",
            "7. dividend amount": "0.0000",
            "8. split coefficient": "1.0000"
        },
        "2017-08-03": {
            "1. open": "54.3400",
            "2. high": "55.6400",
            "3. low": "54.2800",
            "4. close": "55.5500",
            "5. adjusted close": "54.7846",
            "6. volume": "705447",
            "7. dividend amount": "0.0000",
            "8. split coefficient": "1.0000"
        },
        "2017-08-02": {
            "1. open": "55.7200",
            "2. high": "56.0100",
            "3. low": "55.5300",
            "4. close": "55.6700",
            "5. adjusted close": "54.9030",
            "6. volume": "239102",
            "7. dividend amount": "0.0000",
            "8. split coefficient": "1.0000"
        },
        "2017-08-01": {
            "1. open": "55.7400",
            "2. high": "56.0700",
            "3. low": "55.7400",
            "4. close": "55.8500",
            "5. adjusted close": "55.0805",
            "6. volume": "179387",
            "7. dividend amount": "0.0000",
            "8. split coefficient": "1.0000"
        },
        "2017-07-31": {
            "1. open": "56.0100",
            "2. high": "56.0100",
            "3. low": "55.7500",
            "4. close": "55.8600",
            "5. adjusted close": "55.0903",
            "6. volume": "448576",
            "7. dividend amount": "0.0000",
            "8. split coefficient": "1.0000"
        },
        "2017-07-28": {
            "1. open": "55.9200",
            "2. high": "56.3000",
            "3. low": "55.8100",
            "4. close": "56.0100",
            "5. adjusted close": "55.2383",
            "6. volume": "493641",
            "7. dividend amount": "0.0000",
            "8. split coefficient": "1.0000"
        },
        "2017-07-27": {
            "1. open": "56.1500",
            "2. high": "56.1500",
            "3. low": "55.6600",
            "4. close": "55.9200",
            "5. adjusted close": "55.1495",
            "6. volume": "4693323",
            "7. dividend amount": "0.0000",
            "8. split coefficient": "1.0000"
        },
        "2017-07-26": {
            "1. open": "56.2200",
            "2. high": "56.7500",
            "3. low": "55.8600",
            "4. close": "55.9800",
            "5. adjusted close": "55.2087",
            "6. volume": "284727",
            "7. dividend amount": "0.0000",
            "8. split coefficient": "1.0000"
        },
        "2017-07-25": {
            "1. open": "56.6800",
            "2. high": "56.6800",
            "3. low": "56.0200",
            "4. close": "56.1800",
            "5. adjusted close": "55.4059",
            "6. volume": "218635",
            "7. dividend amount": "0.0000",
            "8. split coefficient": "1.0000"
        },
        "2017-07-24": {
            "1. open": "56.7500",
            "2. high": "56.7500",
            "3. low": "56.2400",
            "4. close": "56.3600",
            "5. adjusted close": "55.5835",
            "6. volume": "353594",
            "7. dividend amount": "0.0000",
            "8. split coefficient": "1.0000"
        },
        "2017-07-21": {
            "1. open": "56.0400",
            "2. high": "56.6900",
            "3. low": "56.0000",
            "4. close": "56.5900",
            "5. adjusted close": "55.8103",
            "6. volume": "7880192",
            "7. dividend amount": "0.0000",
            "8. split coefficient": "1.0000"
        },
        "2017-07-20": {
            "1. open": "55.8900",
            "2. high": "56.1200",
            "3. low": "55.5300",
            "4. close": "55.9800",
            "5. adjusted close": "55.2087",
            "6. volume": "624924",
            "7. dividend amount": "0.0000",
            "8. split coefficient": "1.0000"
        },
        "2017-07-19": {
            "1. open": "55.5500",
            "2. high": "55.8400",
            "3. low": "55.3400",
            "4. close": "55.7000",
            "5. adjusted close": "54.9325",
            "6. volume": "1022093",
            "7. dividend amount": "0.0000",
            "8. split coefficient": "1.0000"
        },
        "2017-07-18": {
            "1. open": "55.1500",
            "2. high": "55.4900",
            "3. low": "55.0100",
            "4. close": "55.4100",
            "5. adjusted close": "54.6465",
            "6. volume": "530930",
            "7. dividend amount": "0.0000",
            "8. split coefficient": "1.0000"
        },
        "2017-07-17": {
            "1. open": "55.3900",
            "2. high": "55.4000",
            "3. low": "55.0360",
            "4. close": "55.1000",
            "5. adjusted close": "54.3408",
            "6. volume": "446903",
            "7. dividend amount": "0.0000",
            "8. split coefficient": "1.0000"
        },
        "2017-07-14": {
            "1. open": "54.8200",
            "2. high": "55.2600",
            "3. low": "54.5200",
            "4. close": "55.2600",
            "5. adjusted close": "54.4986",
            "6. volume": "689616",
            "7. dividend amount": "0.0000",
            "8. split coefficient": "1.0000"
        },
        "2017-07-13": {
            "1. open": "54.6000",
            "2. high": "54.7500",
            "3. low": "54.4800",
            "4. close": "54.6400",
            "5. adjusted close": "53.8872",
            "6. volume": "439736",
            "7. dividend amount": "0.0000",
            "8. split coefficient": "1.0000"
        },
        "2017-07-12": {
            "1. open": "54.6100",
            "2. high": "56.1900",
            "3. low": "54.4800",
            "4. close": "54.6000",
            "5. adjusted close": "53.8477",
            "6. volume": "1299031",
            "7. dividend amount": "0.6550",
            "8. split coefficient": "1.0000"
        },
        "2017-07-11": {
            "1. open": "55.0100",
            "2. high": "55.3000",
            "3. low": "54.8600",
            "4. close": "54.9400",
            "5. adjusted close": "53.5407",
            "6. volume": "848181",
            "7. dividend amount": "0.0000",
            "8. split coefficient": "1.0000"
        },
        "2017-07-10": {
            "1. open": "55.4600",
            "2. high": "55.5000",
            "3. low": "55.0700",
            "4. close": "55.3000",
            "5. adjusted close": "53.8916",
            "6. volume": "892431",
            "7. dividend amount": "0.0000",
            "8. split coefficient": "1.0000"
        },
        "2017-07-07": {
            "1. open": "55.1000",
            "2. high": "55.3600",
            "3. low": "54.6800",
            "4. close": "55.3600",
            "5. adjusted close": "53.9500",
            "6. volume": "467823",
            "7. dividend amount": "0.0000",
            "8. split coefficient": "1.0000"
        },
        "2017-07-06": {
            "1. open": "54.9900",
            "2. high": "55.0500",
            "3. low": "54.6560",
            "4. close": "54.9000",
            "5. adjusted close": "53.5017",
            "6. volume": "599862",
            "7. dividend amount": "0.0000",
            "8. split coefficient": "1.0000"
        },
        "2017-07-05": {
            "1. open": "54.7200",
            "2. high": "55.0700",
            "3. low": "54.5000",
            "4. close": "55.0600",
            "5. adjusted close": "53.6577",
            "6. volume": "453509",
            "7. dividend amount": "0.0000",
            "8. split coefficient": "1.0000"
        },
        "2017-07-03": {
            "1. open": "54.8300",
            "2. high": "54.9600",
            "3. low": "54.5500",
            "4. close": "54.7000",
            "5. adjusted close": "53.3068",
            "6. volume": "74651",
            "7. dividend amount": "0.0000",
            "8. split coefficient": "1.0000"
        },
        "2017-06-30": {
            "1. open": "54.9000",
            "2. high": "56.2500",
            "3. low": "54.6800",
            "4. close": "54.7800",
            "5. adjusted close": "53.3848",
            "6. volume": "634630",
            "7. dividend amount": "0.0000",
            "8. split coefficient": "1.0000"
        },
        "2017-06-29": {
            "1. open": "54.9300",
            "2. high": "54.9300",
            "3. low": "54.1600",
            "4. close": "54.2300",
            "5. adjusted close": "52.8488",
            "6. volume": "319056",
            "7. dividend amount": "0.0000",
            "8. split coefficient": "1.0000"
        },
        "2017-06-28": {
            "1. open": "54.6300",
            "2. high": "55.2500",
            "3. low": "54.5500",
            "4. close": "54.7000",
            "5. adjusted close": "53.3068",
            "6. volume": "418465",
            "7. dividend amount": "0.0000",
            "8. split coefficient": "1.0000"
        },
        "2017-06-27": {
            "1. open": "54.5500",
            "2. high": "54.9000",
            "3. low": "54.3200",
            "4. close": "54.7500",
            "5. adjusted close": "53.3556",
            "6. volume": "2019878",
            "7. dividend amount": "0.0000",
            "8. split coefficient": "1.0000"
        },
        "2017-06-26": {
            "1. open": "54.8100",
            "2. high": "55.8800",
            "3. low": "54.2500",
            "4. close": "54.5600",
            "5. adjusted close": "53.1704",
            "6. volume": "715785",
            "7. dividend amount": "0.0000",
            "8. split coefficient": "1.0000"
        },
        "2017-06-23": {
            "1. open": "55.6500",
            "2. high": "55.6500",
            "3. low": "54.4100",
            "4. close": "54.6300",
            "5. adjusted close": "53.2386",
            "6. volume": "1310263",
            "7. dividend amount": "0.0000",
            "8. split coefficient": "1.0000"
        },
        "2017-06-22": {
            "1. open": "54.9500",
            "2. high": "54.9500",
            "3. low": "54.1500",
            "4. close": "54.5000",
            "5. adjusted close": "53.1119",
            "6. volume": "735335",
            "7. dividend amount": "0.0000",
            "8. split coefficient": "1.0000"
        },
        "2017-06-21": {
            "1. open": "54.4600",
            "2. high": "54.5300",
            "3. low": "54.1110",
            "4. close": "54.4500",
            "5. adjusted close": "53.0632",
            "6. volume": "299810",
            "7. dividend amount": "0.0000",
            "8. split coefficient": "1.0000"
        },
        "2017-06-20": {
            "1. open": "54.3900",
            "2. high": "56.1100",
            "3. low": "54.3000",
            "4. close": "54.5000",
            "5. adjusted close": "53.1119",
            "6. volume": "507617",
            "7. dividend amount": "0.0000",
            "8. split coefficient": "1.0000"
        },
        "2017-06-19": {
            "1. open": "54.3800",
            "2. high": "54.3900",
            "3. low": "53.9000",
            "4. close": "54.1900",
            "5. adjusted close": "52.8098",
            "6. volume": "335850",
            "7. dividend amount": "0.0000",
            "8. split coefficient": "1.0000"
        },
        "2017-06-16": {
            "1. open": "54.1300",
            "2. high": "54.1300",
            "3. low": "53.6600",
            "4. close": "53.8300",
            "5. adjusted close": "52.4590",
            "6. volume": "138826",
            "7. dividend amount": "0.0000",
            "8. split coefficient": "1.0000"
        },
        "2017-06-15": {
            "1. open": "54.2100",
            "2. high": "55.7100",
            "3. low": "53.7200",
            "4. close": "53.8500",
            "5. adjusted close": "52.4785",
            "6. volume": "928506",
            "7. dividend amount": "0.0000",
            "8. split coefficient": "1.0000"
        },
        "2017-06-14": {
            "1. open": "54.1700",
            "2. high": "54.3500",
            "3. low": "53.8500",
            "4. close": "54.0800",
            "5. adjusted close": "52.7026",
            "6. volume": "201345",
            "7. dividend amount": "0.0000",
            "8. split coefficient": "1.0000"
        },
        "2017-06-13": {
            "1. open": "53.9000",
            "2. high": "54.0900",
            "3. low": "53.8700",
            "4. close": "54.0800",
            "5. adjusted close": "52.7026",
            "6. volume": "346854",
            "7. dividend amount": "0.0000",
            "8. split coefficient": "1.0000"
        },
        "2017-06-12": {
            "1. open": "53.8000",
            "2. high": "53.9200",
            "3. low": "53.5200",
            "4. close": "53.9200",
            "5. adjusted close": "52.5467",
            "6. volume": "389783",
            "7. dividend amount": "0.0000",
            "8. split coefficient": "1.0000"
        },
        "2017-06-09": {
            "1. open": "54.1800",
            "2. high": "54.1800",
            "3. low": "53.7800",
            "4. close": "54.0300",
            "5. adjusted close": "52.6539",
            "6. volume": "163885",
            "7. dividend amount": "0.0000",
            "8. split coefficient": "1.0000"
        },
        "2017-06-08": {
            "1. open": "53.9500",
            "2. high": "54.3000",
            "3. low": "53.6400",
            "4. close": "53.7400",
            "5. adjusted close": "52.3713",
            "6. volume": "1019555",
            "7. dividend amount": "0.0000",
            "8. split coefficient": "1.0000"
        },
        "2017-06-07": {
            "1. open": "54.0000",
            "2. high": "54.2400",
            "3. low": "53.9490",
            "4. close": "54.0480",
            "5. adjusted close": "52.6714",
            "6. volume": "495713",
            "7. dividend amount": "0.0000",
            "8. split coefficient": "1.0000"
        },
        "2017-06-06": {
            "1. open": "54.0200",
            "2. high": "54.3000",
            "3. low": "53.7100",
            "4. close": "53.8100",
            "5. adjusted close": "52.4395",
            "6. volume": "639867",
            "7. dividend amount": "0.0000",
            "8. split coefficient": "1.0000"
        },
        "2017-06-05": {
            "1. open": "54.2600",
            "2. high": "54.2900",
            "3. low": "53.9700",
            "4. close": "53.9700",
            "5. adjusted close": "52.5954",
            "6. volume": "333817",
            "7. dividend amount": "0.0000",
            "8. split coefficient": "1.0000"
        },
        "2017-06-02": {
            "1. open": "53.9200",
            "2. high": "54.1400",
            "3. low": "53.8700",
            "4. close": "54.0500",
            "5. adjusted close": "52.6734",
            "6. volume": "628556",
            "7. dividend amount": "0.0000",
            "8. split coefficient": "1.0000"
        },
        "2017-06-01": {
            "1. open": "53.3200",
            "2. high": "54.0000",
            "3. low": "53.1200",
            "4. close": "53.9200",
            "5. adjusted close": "52.5467",
            "6. volume": "678619",
            "7. dividend amount": "0.0000",
            "8. split coefficient": "1.0000"
        },
        "2017-05-31": {
            "1. open": "53.5900",
            "2. high": "53.5900",
            "3. low": "53.1200",
            "4. close": "53.5100",
            "5. adjusted close": "52.1471",
            "6. volume": "1657049",
            "7. dividend amount": "0.0000",
            "8. split coefficient": "1.0000"
        },
        "2017-05-30": {
            "1. open": "52.6900",
            "2. high": "53.1500",
            "3. low": "52.4300",
            "4. close": "53.0000",
            "5. adjusted close": "51.6501",
            "6. volume": "1252484",
            "7. dividend amount": "0.0000",
            "8. split coefficient": "1.0000"
        },
        "2017-05-26": {
            "1. open": "53.0000",
            "2. high": "53.2300",
            "3. low": "52.5000",
            "4. close": "52.6000",
            "5. adjusted close": "51.2603",
            "6. volume": "213825",
            "7. dividend amount": "0.0000",
            "8. split coefficient": "1.0000"
        },
        "2017-05-25": {
            "1. open": "52.9700",
            "2. high": "53.0000",
            "3. low": "52.5900",
            "4. close": "53.0000",
            "5. adjusted close": "51.6501",
            "6. volume": "309726",
            "7. dividend amount": "0.0000",
            "8. split coefficient": "1.0000"
        },
        "2017-05-24": {
            "1. open": "52.8500",
            "2. high": "52.8700",
            "3. low": "52.5410",
            "4. close": "52.8070",
            "5. adjusted close": "51.4621",
            "6. volume": "509638",
            "7. dividend amount": "0.0000",
            "8. split coefficient": "1.0000"
        },
        "2017-05-23": {
            "1. open": "52.5200",
            "2. high": "52.8900",
            "3. low": "52.5200",
            "4. close": "52.8400",
            "5. adjusted close": "51.4942",
            "6. volume": "524954",
            "7. dividend amount": "0.0000",
            "8. split coefficient": "1.0000"
        },
        "2017-05-22": {
            "1. open": "52.3700",
            "2. high": "52.7100",
            "3. low": "52.2510",
            "4. close": "52.4500",
            "5. adjusted close": "51.1141",
            "6. volume": "1299151",
            "7. dividend amount": "0.0000",
            "8. split coefficient": "1.0000"
        },
        "2017-05-19": {
            "1. open": "52.0100",
            "2. high": "52.9900",
            "3. low": "52.0100",
            "4. close": "52.3700",
            "5. adjusted close": "51.0362",
            "6. volume": "688350",
            "7. dividend amount": "0.0000",
            "8. split coefficient": "1.0000"
        },
        "2017-05-18": {
            "1. open": "52.2500",
            "2. high": "52.4400",
            "3. low": "51.8500",
            "4. close": "52.1700",
            "5. adjusted close": "50.8413",
            "6. volume": "741452",
            "7. dividend amount": "0.0000",
            "8. split coefficient": "1.0000"
        },
        "2017-05-17": {
            "1. open": "52.2500",
            "2. high": "53.5000",
            "3. low": "51.6300",
            "4. close": "52.0800",
            "5. adjusted close": "50.7536",
            "6. volume": "1496074",
            "7. dividend amount": "0.0000",
            "8. split coefficient": "1.0000"
        },
        "2017-05-16": {
            "1. open": "52.7800",
            "2. high": "52.8500",
            "3. low": "51.8800",
            "4. close": "52.1800",
            "5. adjusted close": "50.8510",
            "6. volume": "1507223",
            "7. dividend amount": "0.0000",
            "8. split coefficient": "1.0000"
        },
        "2017-05-15": {
            "1. open": "52.2000",
            "2. high": "52.8000",
            "3. low": "52.0000",
            "4. close": "52.5500",
            "5. adjusted close": "51.2116",
            "6. volume": "2380114",
            "7. dividend amount": "0.0000",
            "8. split coefficient": "1.0000"
        },
        "2017-05-12": {
            "1. open": "52.1000",
            "2. high": "53.5000",
            "3. low": "51.7500",
            "4. close": "52.6000",
            "5. adjusted close": "51.2603",
            "6. volume": "27711",
            "7. dividend amount": "0.0000",
            "8. split coefficient": "1.0000"
        },
        "2017-05-11": {
            "1. open": "51.7500",
            "2. high": "52.4000",
            "3. low": "50.2000",
            "4. close": "52.2000",
            "5. adjusted close": "50.8705",
            "6. volume": "2705362",
            "7. dividend amount": "0.0000",
            "8. split coefficient": "1.0000"
        }
    }
}