{
    "Meta Data": {
        "1. Information": "Daily Time Series with Splits and Dividend Events",
        "2. Symbol": "CLPR",
        "3. Last Refreshed": "2017-12-01",
        "4. Output Size": "Full size",
        "5. Time Zone": "US/Eastern"
    },
    "Time Series (Daily)": {
        "2017-12-01": {
            "1. open": "10.1000",
            "2. high": "10.1600",
            "3. low": "9.8200",
            "4. close": "10.1500",
            "5. adjusted close": "10.1500",
            "6. volume": "24815",
            "7. dividend amount": "0.0000",
            "8. split coefficient": "1.0000"
        },
        "2017-11-30": {
            "1. open": "10.2800",
            "2. high": "10.2800",
            "3. low": "10.0000",
            "4. close": "10.0800",
            "5. adjusted close": "10.0800",
            "6. volume": "28016",
            "7. dividend amount": "0.0000",
            "8. split coefficient": "1.0000"
        },
        "2017-11-29": {
            "1. open": "10.2700",
            "2. high": "10.3500",
            "3. low": "10.0000",
            "4. close": "10.2000",
            "5. adjusted close": "10.2000",
            "6. volume": "31703",
            "7. dividend amount": "0.0000",
            "8. split coefficient": "1.0000"
        },
        "2017-11-28": {
            "1. open": "10.3800",
            "2. high": "10.3800",
            "3. low": "10.0800",
            "4. close": "10.2700",
            "5. adjusted close": "10.2700",
            "6. volume": "41816",
            "7. dividend amount": "0.0000",
            "8. split coefficient": "1.0000"
        },
        "2017-11-27": {
            "1. open": "10.5100",
            "2. high": "10.5500",
            "3. low": "10.2600",
            "4. close": "10.3400",
            "5. adjusted close": "10.3400",
            "6. volume": "50619",
            "7. dividend amount": "0.0000",
            "8. split coefficient": "1.0000"
        },
        "2017-11-24": {
            "1. open": "10.5700",
            "2. high": "10.7200",
            "3. low": "10.5130",
            "4. close": "10.5500",
            "5. adjusted close": "10.5500",
            "6. volume": "21811",
            "7. dividend amount": "0.0000",
            "8. split coefficient": "1.0000"
        },
        "2017-11-22": {
            "1. open": "10.4500",
            "2. high": "10.6000",
            "3. low": "10.3500",
            "4. close": "10.5200",
            "5. adjusted close": "10.5200",
            "6. volume": "24557",
            "7. dividend amount": "0.0000",
            "8. split coefficient": "1.0000"
        },
        "2017-11-21": {
            "1. open": "10.4000",
            "2. high": "10.6500",
            "3. low": "10.3300",
            "4. close": "10.4500",
            "5. adjusted close": "10.4500",
            "6. volume": "29112",
            "7. dividend amount": "0.0000",
            "8. split coefficient": "1.0000"
        },
        "2017-11-20": {
            "1. open": "10.0000",
            "2. high": "10.3500",
            "3. low": "10.0000",
            "4. close": "10.3400",
            "5. adjusted close": "10.3400",
            "6. volume": "33181",
            "7. dividend amount": "0.0000",
            "8. split coefficient": "1.0000"
        },
        "2017-11-17": {
            "1. open": "9.8500",
            "2. high": "10.0700",
            "3. low": "9.5700",
            "4. close": "9.9800",
            "5. adjusted close": "9.9800",
            "6. volume": "34448",
            "7. dividend amount": "0.0000",
            "8. split coefficient": "1.0000"
        },
        "2017-11-16": {
            "1. open": "9.7300",
            "2. high": "9.9500",
            "3. low": "9.5900",
            "4. close": "9.8900",
            "5. adjusted close": "9.8900",
            "6. volume": "22711",
            "7. dividend amount": "0.0000",
            "8. split coefficient": "1.0000"
        },
        "2017-11-15": {
            "1. open": "9.8300",
            "2. high": "9.9900",
            "3. low": "9.4300",
            "4. close": "9.6500",
            "5. adjusted close": "9.6500",
            "6. volume": "79480",
            "7. dividend amount": "0.0000",
            "8. split coefficient": "1.0000"
        },
        "2017-11-14": {
            "1. open": "10.5500",
            "2. high": "10.5550",
            "3. low": "9.6600",
            "4. close": "9.8600",
            "5. adjusted close": "9.8600",
            "6. volume": "224537",
            "7. dividend amount": "0.0000",
            "8. split coefficient": "1.0000"
        },
        "2017-11-13": {
            "1. open": "10.9600",
            "2. high": "10.9600",
            "3. low": "10.5500",
            "4. close": "10.5900",
            "5. adjusted close": "10.5900",
            "6. volume": "59824",
            "7. dividend amount": "0.0000",
            "8. split coefficient": "1.0000"
        },
        "2017-11-10": {
            "1. open": "11.1000",
            "2. high": "11.2000",
            "3. low": "10.9600",
            "4. close": "11.0000",
            "5. adjusted close": "11.0000",
            "6. volume": "40885",
            "7. dividend amount": "0.0000",
            "8. split coefficient": "1.0000"
        },
        "2017-11-09": {
            "1. open": "10.8200",
            "2. high": "11.2200",
            "3. low": "10.7600",
            "4. close": "11.0500",
            "5. adjusted close": "11.0500",
            "6. volume": "51481",
            "7. dividend amount": "0.0000",
            "8. split coefficient": "1.0000"
        },
        "2017-11-08": {
            "1. open": "10.5900",
            "2. high": "10.8500",
            "3. low": "10.5030",
            "4. close": "10.7900",
            "5. adjusted close": "10.7900",
            "6. volume": "29961",
            "7. dividend amount": "0.0000",
            "8. split coefficient": "1.0000"
        },
        "2017-11-07": {
            "1. open": "10.7000",
            "2. high": "10.8400",
            "3. low": "10.5900",
            "4. close": "10.6600",
            "5. adjusted close": "10.6600",
            "6. volume": "52264",
            "7. dividend amount": "0.0000",
            "8. split coefficient": "1.0000"
        },
        "2017-11-06": {
            "1. open": "11.0800",
            "2. high": "11.0800",
            "3. low": "10.5000",
            "4. close": "10.7100",
            "5. adjusted close": "10.7100",
            "6. volume": "51098",
            "7. dividend amount": "0.0000",
            "8. split coefficient": "1.0000"
        },
        "2017-11-03": {
            "1. open": "11.0000",
            "2. high": "11.0900",
            "3. low": "10.8640",
            "4. close": "11.0000",
            "5. adjusted close": "11.0000",
            "6. volume": "109765",
            "7. dividend amount": "0.0950",
            "8. split coefficient": "1.0000"
        },
        "2017-11-02": {
            "1. open": "10.8500",
            "2. high": "11.0000",
            "3. low": "10.8500",
            "4. close": "10.9800",
            "5. adjusted close": "10.8860",
            "6. volume": "16746",
            "7. dividend amount": "0.0000",
            "8. split coefficient": "1.0000"
        },
        "2017-11-01": {
            "1. open": "10.9500",
            "2. high": "11.1200",
            "3. low": "10.8200",
            "4. close": "10.8500",
            "5. adjusted close": "10.7571",
            "6. volume": "32746",
            "7. dividend amount": "0.0000",
            "8. split coefficient": "1.0000"
        },
        "2017-10-31": {
            "1. open": "10.8000",
            "2. high": "10.9000",
            "3. low": "10.8000",
            "4. close": "10.8700",
            "5. adjusted close": "10.7769",
            "6. volume": "29600",
            "7. dividend amount": "0.0000",
            "8. split coefficient": "1.0000"
        },
        "2017-10-30": {
            "1. open": "10.7600",
            "2. high": "10.8200",
            "3. low": "10.6500",
            "4. close": "10.8000",
            "5. adjusted close": "10.7075",
            "6. volume": "56187",
            "7. dividend amount": "0.0000",
            "8. split coefficient": "1.0000"
        },
        "2017-10-27": {
            "1. open": "11.0300",
            "2. high": "11.0900",
            "3. low": "10.7200",
            "4. close": "10.7600",
            "5. adjusted close": "10.6679",
            "6. volume": "38757",
            "7. dividend amount": "0.0000",
            "8. split coefficient": "1.0000"
        },
        "2017-10-26": {
            "1. open": "11.1000",
            "2. high": "11.3800",
            "3. low": "10.9500",
            "4. close": "11.1100",
            "5. adjusted close": "11.0149",
            "6. volume": "38962",
            "7. dividend amount": "0.0000",
            "8. split coefficient": "1.0000"
        },
        "2017-10-25": {
            "1. open": "10.8800",
            "2. high": "11.0400",
            "3. low": "10.8800",
            "4. close": "11.0200",
            "5. adjusted close": "10.9256",
            "6. volume": "20721",
            "7. dividend amount": "0.0000",
            "8. split coefficient": "1.0000"
        },
        "2017-10-24": {
            "1. open": "11.0300",
            "2. high": "11.0300",
            "3. low": "10.9000",
            "4. close": "10.9100",
            "5. adjusted close": "10.8166",
            "6. volume": "31303",
            "7. dividend amount": "0.0000",
            "8. split coefficient": "1.0000"
        },
        "2017-10-23": {
            "1. open": "11.3500",
            "2. high": "11.3500",
            "3. low": "10.9100",
            "4. close": "10.9200",
            "5. adjusted close": "10.8265",
            "6. volume": "26821",
            "7. dividend amount": "0.0000",
            "8. split coefficient": "1.0000"
        },
        "2017-10-20": {
            "1. open": "11.4900",
            "2. high": "11.6700",
            "3. low": "11.3300",
            "4. close": "11.3500",
            "5. adjusted close": "11.2528",
            "6. volume": "34580",
            "7. dividend amount": "0.0000",
            "8. split coefficient": "1.0000"
        },
        "2017-10-19": {
            "1. open": "11.3800",
            "2. high": "11.4400",
            "3. low": "11.1750",
            "4. close": "11.4400",
            "5. adjusted close": "11.3420",
            "6. volume": "24422",
            "7. dividend amount": "0.0000",
            "8. split coefficient": "1.0000"
        },
        "2017-10-18": {
            "1. open": "11.5300",
            "2. high": "11.5300",
            "3. low": "11.3940",
            "4. close": "11.4000",
            "5. adjusted close": "11.3024",
            "6. volume": "12601",
            "7. dividend amount": "0.0000",
            "8. split coefficient": "1.0000"
        },
        "2017-10-17": {
            "1. open": "11.5800",
            "2. high": "11.6000",
            "3. low": "11.2000",
            "4. close": "11.4800",
            "5. adjusted close": "11.3817",
            "6. volume": "61064",
            "7. dividend amount": "0.0000",
            "8. split coefficient": "1.0000"
        },
        "2017-10-16": {
            "1. open": "11.5000",
            "2. high": "11.5400",
            "3. low": "11.4000",
            "4. close": "11.5000",
            "5. adjusted close": "11.4015",
            "6. volume": "38346",
            "7. dividend amount": "0.0000",
            "8. split coefficient": "1.0000"
        },
        "2017-10-13": {
            "1. open": "11.5000",
            "2. high": "11.5300",
            "3. low": "11.3240",
            "4. close": "11.5100",
            "5. adjusted close": "11.4114",
            "6. volume": "16980",
            "7. dividend amount": "0.0000",
            "8. split coefficient": "1.0000"
        },
        "2017-10-12": {
            "1. open": "11.5300",
            "2. high": "11.5700",
            "3. low": "11.3730",
            "4. close": "11.4800",
            "5. adjusted close": "11.3817",
            "6. volume": "36523",
            "7. dividend amount": "0.0000",
            "8. split coefficient": "1.0000"
        },
        "2017-10-11": {
            "1. open": "11.5500",
            "2. high": "11.5900",
            "3. low": "11.5000",
            "4. close": "11.5400",
            "5. adjusted close": "11.4412",
            "6. volume": "51863",
            "7. dividend amount": "0.0000",
            "8. split coefficient": "1.0000"
        },
        "2017-10-10": {
            "1. open": "11.4800",
            "2. high": "11.6000",
            "3. low": "11.3800",
            "4. close": "11.5600",
            "5. adjusted close": "11.4610",
            "6. volume": "96174",
            "7. dividend amount": "0.0000",
            "8. split coefficient": "1.0000"
        },
        "2017-10-09": {
            "1. open": "11.1600",
            "2. high": "11.7200",
            "3. low": "11.1600",
            "4. close": "11.4000",
            "5. adjusted close": "11.3024",
            "6. volume": "104181",
            "7. dividend amount": "0.0000",
            "8. split coefficient": "1.0000"
        },
        "2017-10-06": {
            "1. open": "10.8900",
            "2. high": "11.0200",
            "3. low": "10.5900",
            "4. close": "10.9600",
            "5. adjusted close": "10.8662",
            "6. volume": "18957",
            "7. dividend amount": "0.0000",
            "8. split coefficient": "1.0000"
        },
        "2017-10-05": {
            "1. open": "10.8900",
            "2. high": "11.1000",
            "3. low": "10.8330",
            "4. close": "10.9100",
            "5. adjusted close": "10.8166",
            "6. volume": "23957",
            "7. dividend amount": "0.0000",
            "8. split coefficient": "1.0000"
        },
        "2017-10-04": {
            "1. open": "10.8300",
            "2. high": "11.0800",
            "3. low": "10.8000",
            "4. close": "10.8700",
            "5. adjusted close": "10.7769",
            "6. volume": "19849",
            "7. dividend amount": "0.0000",
            "8. split coefficient": "1.0000"
        },
        "2017-10-03": {
            "1. open": "10.9900",
            "2. high": "11.0100",
            "3. low": "10.8500",
            "4. close": "10.8800",
            "5. adjusted close": "10.7868",
            "6. volume": "25188",
            "7. dividend amount": "0.0000",
            "8. split coefficient": "1.0000"
        },
        "2017-10-02": {
            "1. open": "10.7100",
            "2. high": "10.9900",
            "3. low": "10.7000",
            "4. close": "10.9700",
            "5. adjusted close": "10.8761",
            "6. volume": "26814",
            "7. dividend amount": "0.0000",
            "8. split coefficient": "1.0000"
        },
        "2017-09-29": {
            "1. open": "10.9200",
            "2. high": "10.9700",
            "3. low": "10.6100",
            "4. close": "10.7100",
            "5. adjusted close": "10.6183",
            "6. volume": "35446",
            "7. dividend amount": "0.0000",
            "8. split coefficient": "1.0000"
        },
        "2017-09-28": {
            "1. open": "11.2800",
            "2. high": "11.2800",
            "3. low": "10.5400",
            "4. close": "10.9600",
            "5. adjusted close": "10.8662",
            "6. volume": "49343",
            "7. dividend amount": "0.0000",
            "8. split coefficient": "1.0000"
        },
        "2017-09-27": {
            "1. open": "10.8700",
            "2. high": "11.3500",
            "3. low": "10.4600",
            "4. close": "11.2200",
            "5. adjusted close": "11.1239",
            "6. volume": "115573",
            "7. dividend amount": "0.0000",
            "8. split coefficient": "1.0000"
        },
        "2017-09-26": {
            "1. open": "10.5300",
            "2. high": "10.7970",
            "3. low": "10.5300",
            "4. close": "10.7500",
            "5. adjusted close": "10.6580",
            "6. volume": "25498",
            "7. dividend amount": "0.0000",
            "8. split coefficient": "1.0000"
        },
        "2017-09-25": {
            "1. open": "10.3400",
            "2. high": "10.6400",
            "3. low": "10.2400",
            "4. close": "10.5900",
            "5. adjusted close": "10.4993",
            "6. volume": "67076",
            "7. dividend amount": "0.0000",
            "8. split coefficient": "1.0000"
        },
        "2017-09-22": {
            "1. open": "10.5800",
            "2. high": "10.6300",
            "3. low": "10.3900",
            "4. close": "10.4100",
            "5. adjusted close": "10.3209",
            "6. volume": "44185",
            "7. dividend amount": "0.0000",
            "8. split coefficient": "1.0000"
        },
        "2017-09-21": {
            "1. open": "10.6900",
            "2. high": "10.8600",
            "3. low": "10.5500",
            "4. close": "10.5600",
            "5. adjusted close": "10.4696",
            "6. volume": "38726",
            "7. dividend amount": "0.0000",
            "8. split coefficient": "1.0000"
        },
        "2017-09-20": {
            "1. open": "10.7900",
            "2. high": "11.0800",
            "3. low": "10.6800",
            "4. close": "10.7700",
            "5. adjusted close": "10.6778",
            "6. volume": "115222",
            "7. dividend amount": "0.0000",
            "8. split coefficient": "1.0000"
        },
        "2017-09-19": {
            "1. open": "11.1500",
            "2. high": "11.2000",
            "3. low": "10.8100",
            "4. close": "10.8100",
            "5. adjusted close": "10.7174",
            "6. volume": "91809",
            "7. dividend amount": "0.0000",
            "8. split coefficient": "1.0000"
        },
        "2017-09-18": {
            "1. open": "10.9000",
            "2. high": "11.3300",
            "3. low": "10.7600",
            "4. close": "11.1600",
            "5. adjusted close": "11.0644",
            "6. volume": "129230",
            "7. dividend amount": "0.0000",
            "8. split coefficient": "1.0000"
        },
        "2017-09-15": {
            "1. open": "11.0000",
            "2. high": "11.6300",
            "3. low": "10.2900",
            "4. close": "10.7600",
            "5. adjusted close": "10.6679",
            "6. volume": "318196",
            "7. dividend amount": "0.0000",
            "8. split coefficient": "1.0000"
        },
        "2017-09-14": {
            "1. open": "10.9200",
            "2. high": "11.3700",
            "3. low": "10.9200",
            "4. close": "11.2500",
            "5. adjusted close": "11.1537",
            "6. volume": "195625",
            "7. dividend amount": "0.0000",
            "8. split coefficient": "1.0000"
        },
        "2017-09-13": {
            "1. open": "11.0400",
            "2. high": "11.2400",
            "3. low": "10.9200",
            "4. close": "10.9800",
            "5. adjusted close": "10.8860",
            "6. volume": "155720",
            "7. dividend amount": "0.0000",
            "8. split coefficient": "1.0000"
        },
        "2017-09-12": {
            "1. open": "10.8700",
            "2. high": "11.2400",
            "3. low": "10.8500",
            "4. close": "10.9500",
            "5. adjusted close": "10.8562",
            "6. volume": "80020",
            "7. dividend amount": "0.0000",
            "8. split coefficient": "1.0000"
        },
        "2017-09-11": {
            "1. open": "11.0500",
            "2. high": "11.1200",
            "3. low": "10.8500",
            "4. close": "10.9200",
            "5. adjusted close": "10.8265",
            "6. volume": "125291",
            "7. dividend amount": "0.0000",
            "8. split coefficient": "1.0000"
        },
        "2017-09-08": {
            "1. open": "10.8800",
            "2. high": "11.1700",
            "3. low": "10.7100",
            "4. close": "10.9300",
            "5. adjusted close": "10.8364",
            "6. volume": "89818",
            "7. dividend amount": "0.0000",
            "8. split coefficient": "1.0000"
        },
        "2017-09-07": {
            "1. open": "11.1500",
            "2. high": "11.4000",
            "3. low": "10.5800",
            "4. close": "10.8400",
            "5. adjusted close": "10.7472",
            "6. volume": "95968",
            "7. dividend amount": "0.0000",
            "8. split coefficient": "1.0000"
        },
        "2017-09-06": {
            "1. open": "11.1500",
            "2. high": "11.4900",
            "3. low": "10.9600",
            "4. close": "11.1000",
            "5. adjusted close": "11.0050",
            "6. volume": "113697",
            "7. dividend amount": "0.0000",
            "8. split coefficient": "1.0000"
        },
        "2017-09-05": {
            "1. open": "11.1400",
            "2. high": "11.5000",
            "3. low": "10.8700",
            "4. close": "11.0000",
            "5. adjusted close": "10.9058",
            "6. volume": "177168",
            "7. dividend amount": "0.0000",
            "8. split coefficient": "1.0000"
        },
        "2017-09-01": {
            "1. open": "11.1200",
            "2. high": "11.1250",
            "3. low": "10.9200",
            "4. close": "11.1000",
            "5. adjusted close": "11.0050",
            "6. volume": "16626",
            "7. dividend amount": "0.0000",
            "8. split coefficient": "1.0000"
        },
        "2017-08-31": {
            "1. open": "11.1500",
            "2. high": "11.2500",
            "3. low": "10.9600",
            "4. close": "11.1600",
            "5. adjusted close": "11.0644",
            "6. volume": "47869",
            "7. dividend amount": "0.0000",
            "8. split coefficient": "1.0000"
        },
        "2017-08-30": {
            "1. open": "11.1600",
            "2. high": "11.2300",
            "3. low": "10.9500",
            "4. close": "11.1300",
            "5. adjusted close": "11.0347",
            "6. volume": "18706",
            "7. dividend amount": "0.0000",
            "8. split coefficient": "1.0000"
        },
        "2017-08-29": {
            "1. open": "11.4200",
            "2. high": "11.6000",
            "3. low": "10.9500",
            "4. close": "11.1700",
            "5. adjusted close": "11.0744",
            "6. volume": "66809",
            "7. dividend amount": "0.0000",
            "8. split coefficient": "1.0000"
        },
        "2017-08-28": {
            "1. open": "11.0100",
            "2. high": "11.4400",
            "3. low": "11.0100",
            "4. close": "11.4300",
            "5. adjusted close": "11.3321",
            "6. volume": "49463",
            "7. dividend amount": "0.0000",
            "8. split coefficient": "1.0000"
        },
        "2017-08-25": {
            "1. open": "11.0700",
            "2. high": "11.0800",
            "3. low": "10.9000",
            "4. close": "11.0000",
            "5. adjusted close": "10.9058",
            "6. volume": "10959",
            "7. dividend amount": "0.0000",
            "8. split coefficient": "1.0000"
        },
        "2017-08-24": {
            "1. open": "11.1800",
            "2. high": "11.2200",
            "3. low": "11.0300",
            "4. close": "11.0400",
            "5. adjusted close": "10.9455",
            "6. volume": "29557",
            "7. dividend amount": "0.0000",
            "8. split coefficient": "1.0000"
        },
        "2017-08-23": {
            "1. open": "11.1000",
            "2. high": "11.5000",
            "3. low": "11.1000",
            "4. close": "11.2100",
            "5. adjusted close": "11.1140",
            "6. volume": "130118",
            "7. dividend amount": "0.0000",
            "8. split coefficient": "1.0000"
        },
        "2017-08-22": {
            "1. open": "10.5700",
            "2. high": "11.2300",
            "3. low": "10.4500",
            "4. close": "11.1600",
            "5. adjusted close": "11.0644",
            "6. volume": "59649",
            "7. dividend amount": "0.0000",
            "8. split coefficient": "1.0000"
        },
        "2017-08-21": {
            "1. open": "10.5300",
            "2. high": "10.5900",
            "3. low": "10.4800",
            "4. close": "10.5600",
            "5. adjusted close": "10.4696",
            "6. volume": "18030",
            "7. dividend amount": "0.0000",
            "8. split coefficient": "1.0000"
        },
        "2017-08-18": {
            "1. open": "10.5000",
            "2. high": "10.6800",
            "3. low": "10.4700",
            "4. close": "10.5400",
            "5. adjusted close": "10.4498",
            "6. volume": "36050",
            "7. dividend amount": "0.0000",
            "8. split coefficient": "1.0000"
        },
        "2017-08-17": {
            "1. open": "10.3200",
            "2. high": "10.8600",
            "3. low": "10.3100",
            "4. close": "10.5900",
            "5. adjusted close": "10.4993",
            "6. volume": "90605",
            "7. dividend amount": "0.0000",
            "8. split coefficient": "1.0000"
        },
        "2017-08-16": {
            "1. open": "10.4100",
            "2. high": "10.5500",
            "3. low": "10.3000",
            "4. close": "10.4000",
            "5. adjusted close": "10.3110",
            "6. volume": "25145",
            "7. dividend amount": "0.0000",
            "8. split coefficient": "1.0000"
        },
        "2017-08-15": {
            "1. open": "10.4200",
            "2. high": "10.4800",
            "3. low": "10.2330",
            "4. close": "10.4100",
            "5. adjusted close": "10.3209",
            "6. volume": "27870",
            "7. dividend amount": "0.0000",
            "8. split coefficient": "1.0000"
        },
        "2017-08-14": {
            "1. open": "10.0200",
            "2. high": "10.5300",
            "3. low": "10.0200",
            "4. close": "10.4200",
            "5. adjusted close": "10.3308",
            "6. volume": "51718",
            "7. dividend amount": "0.0000",
            "8. split coefficient": "1.0000"
        },
        "2017-08-11": {
            "1. open": "10.2300",
            "2. high": "10.2300",
            "3. low": "9.9800",
            "4. close": "9.9800",
            "5. adjusted close": "9.8945",
            "6. volume": "223997",
            "7. dividend amount": "0.0000",
            "8. split coefficient": "1.0000"
        },
        "2017-08-10": {
            "1. open": "10.2900",
            "2. high": "10.3100",
            "3. low": "10.1800",
            "4. close": "10.1900",
            "5. adjusted close": "10.1027",
            "6. volume": "49901",
            "7. dividend amount": "0.0000",
            "8. split coefficient": "1.0000"
        },
        "2017-08-09": {
            "1. open": "10.4400",
            "2. high": "10.4500",
            "3. low": "10.2500",
            "4. close": "10.2900",
            "5. adjusted close": "10.2019",
            "6. volume": "71087",
            "7. dividend amount": "0.0000",
            "8. split coefficient": "1.0000"
        },
        "2017-08-08": {
            "1. open": "10.4200",
            "2. high": "10.9100",
            "3. low": "10.4100",
            "4. close": "10.4500",
            "5. adjusted close": "10.3605",
            "6. volume": "177246",
            "7. dividend amount": "0.0000",
            "8. split coefficient": "1.0000"
        },
        "2017-08-07": {
            "1. open": "10.5200",
            "2. high": "10.5500",
            "3. low": "10.1100",
            "4. close": "10.4800",
            "5. adjusted close": "10.3903",
            "6. volume": "42848",
            "7. dividend amount": "0.0000",
            "8. split coefficient": "1.0000"
        },
        "2017-08-04": {
            "1. open": "10.6500",
            "2. high": "10.8000",
            "3. low": "10.5000",
            "4. close": "10.5400",
            "5. adjusted close": "10.4498",
            "6. volume": "37345",
            "7. dividend amount": "0.0000",
            "8. split coefficient": "1.0000"
        },
        "2017-08-03": {
            "1. open": "10.6700",
            "2. high": "11.0000",
            "3. low": "10.6100",
            "4. close": "10.6300",
            "5. adjusted close": "10.5390",
            "6. volume": "44956",
            "7. dividend amount": "0.0950",
            "8. split coefficient": "1.0000"
        },
        "2017-08-02": {
            "1. open": "10.9400",
            "2. high": "10.9400",
            "3. low": "10.5500",
            "4. close": "10.7700",
            "5. adjusted close": "10.5832",
            "6. volume": "59191",
            "7. dividend amount": "0.0000",
            "8. split coefficient": "1.0000"
        },
        "2017-08-01": {
            "1. open": "11.2600",
            "2. high": "11.2600",
            "3. low": "10.5700",
            "4. close": "10.9500",
            "5. adjusted close": "10.7601",
            "6. volume": "44481",
            "7. dividend amount": "0.0000",
            "8. split coefficient": "1.0000"
        },
        "2017-07-31": {
            "1. open": "11.5800",
            "2. high": "11.5800",
            "3. low": "11.1500",
            "4. close": "11.2000",
            "5. adjusted close": "11.0057",
            "6. volume": "23973",
            "7. dividend amount": "0.0000",
            "8. split coefficient": "1.0000"
        },
        "2017-07-28": {
            "1. open": "11.8000",
            "2. high": "11.9000",
            "3. low": "11.5500",
            "4. close": "11.5500",
            "5. adjusted close": "11.3497",
            "6. volume": "28098",
            "7. dividend amount": "0.0000",
            "8. split coefficient": "1.0000"
        },
        "2017-07-27": {
            "1. open": "11.9600",
            "2. high": "12.0200",
            "3. low": "11.8200",
            "4. close": "11.8200",
            "5. adjusted close": "11.6150",
            "6. volume": "37203",
            "7. dividend amount": "0.0000",
            "8. split coefficient": "1.0000"
        },
        "2017-07-26": {
            "1. open": "12.0000",
            "2. high": "12.0150",
            "3. low": "11.8500",
            "4. close": "11.9400",
            "5. adjusted close": "11.7329",
            "6. volume": "16762",
            "7. dividend amount": "0.0000",
            "8. split coefficient": "1.0000"
        },
        "2017-07-25": {
            "1. open": "11.9700",
            "2. high": "12.0500",
            "3. low": "11.9500",
            "4. close": "12.0100",
            "5. adjusted close": "11.8017",
            "6. volume": "27209",
            "7. dividend amount": "0.0000",
            "8. split coefficient": "1.0000"
        },
        "2017-07-24": {
            "1. open": "11.9500",
            "2. high": "12.0700",
            "3. low": "11.9100",
            "4. close": "11.9700",
            "5. adjusted close": "11.7624",
            "6. volume": "29560",
            "7. dividend amount": "0.0000",
            "8. split coefficient": "1.0000"
        },
        "2017-07-21": {
            "1. open": "12.1500",
            "2. high": "12.1500",
            "3. low": "11.8500",
            "4. close": "11.9100",
            "5. adjusted close": "11.7034",
            "6. volume": "37268",
            "7. dividend amount": "0.0000",
            "8. split coefficient": "1.0000"
        },
        "2017-07-20": {
            "1. open": "11.9000",
            "2. high": "12.0300",
            "3. low": "11.8400",
            "4. close": "11.9800",
            "5. adjusted close": "11.7722",
            "6. volume": "59076",
            "7. dividend amount": "0.0000",
            "8. split coefficient": "1.0000"
        },
        "2017-07-19": {
            "1. open": "11.9900",
            "2. high": "12.0950",
            "3. low": "11.8800",
            "4. close": "11.9700",
            "5. adjusted close": "11.7624",
            "6. volume": "21110",
            "7. dividend amount": "0.0000",
            "8. split coefficient": "1.0000"
        },
        "2017-07-18": {
            "1. open": "11.9500",
            "2. high": "12.1200",
            "3. low": "11.9000",
            "4. close": "11.9900",
            "5. adjusted close": "11.7820",
            "6. volume": "72623",
            "7. dividend amount": "0.0000",
            "8. split coefficient": "1.0000"
        },
        "2017-07-17": {
            "1. open": "11.9100",
            "2. high": "12.0900",
            "3. low": "11.8590",
            "4. close": "12.0000",
            "5. adjusted close": "11.7919",
            "6. volume": "91454",
            "7. dividend amount": "0.0000",
            "8. split coefficient": "1.0000"
        },
        "2017-07-14": {
            "1. open": "11.9100",
            "2. high": "12.1000",
            "3. low": "11.8500",
            "4. close": "11.9400",
            "5. adjusted close": "11.7329",
            "6. volume": "24027",
            "7. dividend amount": "0.0000",
            "8. split coefficient": "1.0000"
        },
        "2017-07-13": {
            "1. open": "12.0800",
            "2. high": "12.0800",
            "3. low": "11.9000",
            "4. close": "12.0200",
            "5. adjusted close": "11.8115",
            "6. volume": "35757",
            "7. dividend amount": "0.0000",
            "8. split coefficient": "1.0000"
        },
        "2017-07-12": {
            "1. open": "11.7900",
            "2. high": "12.1900",
            "3. low": "11.7500",
            "4. close": "12.1000",
            "5. adjusted close": "11.8901",
            "6. volume": "37872",
            "7. dividend amount": "0.0000",
            "8. split coefficient": "1.0000"
        },
        "2017-07-11": {
            "1. open": "12.1600",
            "2. high": "12.2600",
            "3. low": "11.6000",
            "4. close": "11.6900",
            "5. adjusted close": "11.4872",
            "6. volume": "35656",
            "7. dividend amount": "0.0000",
            "8. split coefficient": "1.0000"
        },
        "2017-07-10": {
            "1. open": "12.1500",
            "2. high": "12.4550",
            "3. low": "12.0000",
            "4. close": "12.0600",
            "5. adjusted close": "11.8508",
            "6. volume": "27788",
            "7. dividend amount": "0.0000",
            "8. split coefficient": "1.0000"
        },
        "2017-07-07": {
            "1. open": "12.2100",
            "2. high": "12.2100",
            "3. low": "11.9500",
            "4. close": "12.1900",
            "5. adjusted close": "11.9786",
            "6. volume": "17504",
            "7. dividend amount": "0.0000",
            "8. split coefficient": "1.0000"
        },
        "2017-07-06": {
            "1. open": "12.2900",
            "2. high": "12.3000",
            "3. low": "11.8900",
            "4. close": "12.2200",
            "5. adjusted close": "12.0081",
            "6. volume": "23418",
            "7. dividend amount": "0.0000",
            "8. split coefficient": "1.0000"
        },
        "2017-07-05": {
            "1. open": "12.4900",
            "2. high": "12.4900",
            "3. low": "12.1510",
            "4. close": "12.3700",
            "5. adjusted close": "12.1555",
            "6. volume": "36860",
            "7. dividend amount": "0.0000",
            "8. split coefficient": "1.0000"
        },
        "2017-07-03": {
            "1. open": "12.3700",
            "2. high": "12.6100",
            "3. low": "12.0400",
            "4. close": "12.4100",
            "5. adjusted close": "12.1948",
            "6. volume": "33485",
            "7. dividend amount": "0.0000",
            "8. split coefficient": "1.0000"
        },
        "2017-06-30": {
            "1. open": "12.5300",
            "2. high": "12.6300",
            "3. low": "12.3400",
            "4. close": "12.3400",
            "5. adjusted close": "12.1260",
            "6. volume": "52445",
            "7. dividend amount": "0.0000",
            "8. split coefficient": "1.0000"
        },
        "2017-06-29": {
            "1. open": "12.4500",
            "2. high": "12.7600",
            "3. low": "12.3800",
            "4. close": "12.5000",
            "5. adjusted close": "12.2832",
            "6. volume": "51445",
            "7. dividend amount": "0.0000",
            "8. split coefficient": "1.0000"
        },
        "2017-06-28": {
            "1. open": "12.3300",
            "2. high": "12.7300",
            "3. low": "12.0000",
            "4. close": "12.5100",
            "5. adjusted close": "12.2930",
            "6. volume": "104137",
            "7. dividend amount": "0.0000",
            "8. split coefficient": "1.0000"
        },
        "2017-06-27": {
            "1. open": "12.5700",
            "2. high": "12.8200",
            "3. low": "12.1800",
            "4. close": "12.2500",
            "5. adjusted close": "12.0375",
            "6. volume": "73096",
            "7. dividend amount": "0.0000",
            "8. split coefficient": "1.0000"
        },
        "2017-06-26": {
            "1. open": "12.3800",
            "2. high": "12.8800",
            "3. low": "12.3000",
            "4. close": "12.5200",
            "5. adjusted close": "12.3028",
            "6. volume": "166809",
            "7. dividend amount": "0.0000",
            "8. split coefficient": "1.0000"
        },
        "2017-06-23": {
            "1. open": "12.7600",
            "2. high": "12.7800",
            "3. low": "12.0500",
            "4. close": "12.5000",
            "5. adjusted close": "12.2832",
            "6. volume": "899016",
            "7. dividend amount": "0.0000",
            "8. split coefficient": "1.0000"
        },
        "2017-06-22": {
            "1. open": "12.8200",
            "2. high": "12.8500",
            "3. low": "11.8900",
            "4. close": "12.3700",
            "5. adjusted close": "12.1555",
            "6. volume": "113341",
            "7. dividend amount": "0.0000",
            "8. split coefficient": "1.0000"
        },
        "2017-06-21": {
            "1. open": "12.2800",
            "2. high": "12.7600",
            "3. low": "12.2800",
            "4. close": "12.7200",
            "5. adjusted close": "12.4994",
            "6. volume": "48799",
            "7. dividend amount": "0.0000",
            "8. split coefficient": "1.0000"
        },
        "2017-06-20": {
            "1. open": "12.7500",
            "2. high": "12.8300",
            "3. low": "12.1800",
            "4. close": "12.2800",
            "5. adjusted close": "12.0670",
            "6. volume": "43648",
            "7. dividend amount": "0.0000",
            "8. split coefficient": "1.0000"
        },
        "2017-06-19": {
            "1. open": "12.8500",
            "2. high": "12.8500",
            "3. low": "12.6000",
            "4. close": "12.7800",
            "5. adjusted close": "12.5583",
            "6. volume": "72750",
            "7. dividend amount": "0.0000",
            "8. split coefficient": "1.0000"
        },
        "2017-06-16": {
            "1. open": "12.6000",
            "2. high": "12.9900",
            "3. low": "12.6000",
            "4. close": "12.8800",
            "5. adjusted close": "12.6566",
            "6. volume": "328545",
            "7. dividend amount": "0.0000",
            "8. split coefficient": "1.0000"
        },
        "2017-06-15": {
            "1. open": "12.8000",
            "2. high": "13.0000",
            "3. low": "12.6310",
            "4. close": "12.7400",
            "5. adjusted close": "12.5190",
            "6. volume": "57679",
            "7. dividend amount": "0.0000",
            "8. split coefficient": "1.0000"
        },
        "2017-06-14": {
            "1. open": "12.4000",
            "2. high": "12.9500",
            "3. low": "12.3800",
            "4. close": "12.7700",
            "5. adjusted close": "12.5485",
            "6. volume": "211218",
            "7. dividend amount": "0.0000",
            "8. split coefficient": "1.0000"
        },
        "2017-06-13": {
            "1. open": "12.4000",
            "2. high": "12.4000",
            "3. low": "12.0000",
            "4. close": "12.3500",
            "5. adjusted close": "12.1358",
            "6. volume": "112260",
            "7. dividend amount": "0.0000",
            "8. split coefficient": "1.0000"
        },
        "2017-06-12": {
            "1. open": "11.4000",
            "2. high": "12.6200",
            "3. low": "11.3810",
            "4. close": "12.5500",
            "5. adjusted close": "12.3323",
            "6. volume": "85841",
            "7. dividend amount": "0.0000",
            "8. split coefficient": "1.0000"
        },
        "2017-06-09": {
            "1. open": "11.3400",
            "2. high": "11.6300",
            "3. low": "11.1600",
            "4. close": "11.4700",
            "5. adjusted close": "11.2711",
            "6. volume": "769076",
            "7. dividend amount": "0.0000",
            "8. split coefficient": "1.0000"
        },
        "2017-06-08": {
            "1. open": "11.3800",
            "2. high": "11.7500",
            "3. low": "11.3600",
            "4. close": "11.7000",
            "5. adjusted close": "11.4971",
            "6. volume": "35161",
            "7. dividend amount": "0.0000",
            "8. split coefficient": "1.0000"
        },
        "2017-06-07": {
            "1. open": "11.5400",
            "2. high": "11.5400",
            "3. low": "11.3010",
            "4. close": "11.4800",
            "5. adjusted close": "11.2809",
            "6. volume": "24168",
            "7. dividend amount": "0.0000",
            "8. split coefficient": "1.0000"
        },
        "2017-06-06": {
            "1. open": "11.3700",
            "2. high": "11.5500",
            "3. low": "11.3500",
            "4. close": "11.5100",
            "5. adjusted close": "11.3104",
            "6. volume": "30106",
            "7. dividend amount": "0.0000",
            "8. split coefficient": "1.0000"
        },
        "2017-06-05": {
            "1. open": "11.1500",
            "2. high": "11.5000",
            "3. low": "11.1500",
            "4. close": "11.4700",
            "5. adjusted close": "11.2711",
            "6. volume": "23979",
            "7. dividend amount": "0.0000",
            "8. split coefficient": "1.0000"
        },
        "2017-06-02": {
            "1. open": "11.1500",
            "2. high": "11.4500",
            "3. low": "10.9200",
            "4. close": "11.2200",
            "5. adjusted close": "11.0254",
            "6. volume": "43854",
            "7. dividend amount": "0.0000",
            "8. split coefficient": "1.0000"
        },
        "2017-06-01": {
            "1. open": "10.6700",
            "2. high": "11.1000",
            "3. low": "10.6700",
            "4. close": "11.0000",
            "5. adjusted close": "10.8092",
            "6. volume": "38285",
            "7. dividend amount": "0.0000",
            "8. split coefficient": "1.0000"
        },
        "2017-05-31": {
            "1. open": "10.5900",
            "2. high": "10.7600",
            "3. low": "10.5520",
            "4. close": "10.6400",
            "5. adjusted close": "10.4555",
            "6. volume": "18907",
            "7. dividend amount": "0.0000",
            "8. split coefficient": "1.0000"
        },
        "2017-05-30": {
            "1. open": "10.9100",
            "2. high": "10.9100",
            "3. low": "10.6000",
            "4. close": "10.6200",
            "5. adjusted close": "10.4358",
            "6. volume": "24149",
            "7. dividend amount": "0.0000",
            "8. split coefficient": "1.0000"
        },
        "2017-05-26": {
            "1. open": "10.8400",
            "2. high": "10.9100",
            "3. low": "10.8000",
            "4. close": "10.9100",
            "5. adjusted close": "10.7208",
            "6. volume": "30915",
            "7. dividend amount": "0.0000",
            "8. split coefficient": "1.0000"
        },
        "2017-05-25": {
            "1. open": "10.7500",
            "2. high": "10.9700",
            "3. low": "10.7500",
            "4. close": "10.8300",
            "5. adjusted close": "10.6422",
            "6. volume": "44275",
            "7. dividend amount": "0.0000",
            "8. split coefficient": "1.0000"
        },
        "2017-05-24": {
            "1. open": "10.5200",
            "2. high": "10.8900",
            "3. low": "10.5200",
            "4. close": "10.7600",
            "5. adjusted close": "10.5734",
            "6. volume": "50894",
            "7. dividend amount": "0.0000",
            "8. split coefficient": "1.0000"
        },
        "2017-05-23": {
            "1. open": "10.7600",
            "2. high": "10.9490",
            "3. low": "10.4400",
            "4. close": "10.5400",
            "5. adjusted close": "10.3572",
            "6. volume": "65817",
            "7. dividend amount": "0.0950",
            "8. split coefficient": "1.0000"
        },
        "2017-05-22": {
            "1. open": "10.4700",
            "2. high": "10.9500",
            "3. low": "10.4700",
            "4. close": "10.9100",
            "5. adjusted close": "10.6250",
            "6. volume": "15041",
            "7. dividend amount": "0.0000",
            "8. split coefficient": "1.0000"
        },
        "2017-05-19": {
            "1. open": "10.5700",
            "2. high": "10.6000",
            "3. low": "10.3600",
            "4. close": "10.4700",
            "5. adjusted close": "10.1965",
            "6. volume": "45324",
            "7. dividend amount": "0.0000",
            "8. split coefficient": "1.0000"
        },
        "2017-05-18": {
            "1. open": "10.4000",
            "2. high": "10.7000",
            "3. low": "10.3700",
            "4. close": "10.6300",
            "5. adjusted close": "10.3523",
            "6. volume": "58094",
            "7. dividend amount": "0.0000",
            "8. split coefficient": "1.0000"
        },
        "2017-05-17": {
            "1. open": "10.6500",
            "2. high": "10.7300",
            "3. low": "10.3000",
            "4. close": "10.4300",
            "5. adjusted close": "10.1575",
            "6. volume": "83824",
            "7. dividend amount": "0.0000",
            "8. split coefficient": "1.0000"
        },
        "2017-05-16": {
            "1. open": "11.0200",
            "2. high": "11.1000",
            "3. low": "10.7100",
            "4. close": "10.8900",
            "5. adjusted close": "10.6055",
            "6. volume": "60623",
            "7. dividend amount": "0.0000",
            "8. split coefficient": "1.0000"
        },
        "2017-05-15": {
            "1. open": "10.8100",
            "2. high": "11.2400",
            "3. low": "10.8100",
            "4. close": "11.0500",
            "5. adjusted close": "10.7613",
            "6. volume": "101168",
            "7. dividend amount": "0.0000",
            "8. split coefficient": "1.0000"
        },
        "2017-05-12": {
            "1. open": "10.7300",
            "2. high": "10.8400",
            "3. low": "10.7000",
            "4. close": "10.7100",
            "5. adjusted close": "10.4302",
            "6. volume": "49095",
            "7. dividend amount": "0.0000",
            "8. split coefficient": "1.0000"
        },
        "2017-05-11": {
            "1. open": "10.5600",
            "2. high": "10.8400",
            "3. low": "10.4300",
            "4. close": "10.7500",
            "5. adjusted close": "10.4692",
            "6. volume": "44081",
            "7. dividend amount": "0.0000",
            "8. split coefficient": "1.0000"
        },
        "2017-05-10": {
            "1. open": "10.3700",
            "2. high": "10.6600",
            "3. low": "10.0700",
            "4. close": "10.6200",
            "5. adjusted close": "10.3426",
            "6. volume": "106034",
            "7. dividend amount": "0.0000",
            "8. split coefficient": "1.0000"
        },
        "2017-05-09": {
            "1. open": "10.5700",
            "2. high": "10.6550",
            "3. low": "10.3900",
            "4. close": "10.4700",
            "5. adjusted close": "10.1965",
            "6. volume": "123708",
            "7. dividend amount": "0.0000",
            "8. split coefficient": "1.0000"
        },
        "2017-05-08": {
            "1. open": "10.6700",
            "2. high": "10.7400",
            "3. low": "10.6000",
            "4. close": "10.6600",
            "5. adjusted close": "10.3815",
            "6. volume": "69292",
            "7. dividend amount": "0.0000",
            "8. split coefficient": "1.0000"
        },
        "2017-05-05": {
            "1. open": "10.7000",
            "2. high": "10.7900",
            "3. low": "10.5500",
            "4. close": "10.6600",
            "5. adjusted close": "10.3815",
            "6. volume": "118454",
            "7. dividend amount": "0.0000",
            "8. split coefficient": "1.0000"
        },
        "2017-05-04": {
            "1. open": "10.9900",
            "2. high": "11.0000",
            "3. low": "10.7500",
            "4. close": "10.7600",
            "5. adjusted close": "10.4789",
            "6. volume": "62970",
            "7. dividend amount": "0.0000",
            "8. split coefficient": "1.0000"
        },
        "2017-05-03": {
            "1. open": "11.0900",
            "2. high": "11.2200",
            "3. low": "10.9600",
            "4. close": "11.0100",
            "5. adjusted close": "10.7224",
            "6. volume": "44360",
            "7. dividend amount": "0.0000",
            "8. split coefficient": "1.0000"
        },
        "2017-05-02": {
            "1. open": "11.2900",
            "2. high": "11.2900",
            "3. low": "11.1000",
            "4. close": "11.1600",
            "5. adjusted close": "10.8685",
            "6. volume": "59668",
            "7. dividend amount": "0.0000",
            "8. split coefficient": "1.0000"
        },
        "2017-05-01": {
            "1. open": "11.0800",
            "2. high": "11.2400",
            "3. low": "11.0000",
            "4. close": "11.2300",
            "5. adjusted close": "10.9366",
            "6. volume": "35034",
            "7. dividend amount": "0.0000",
            "8. split coefficient": "1.0000"
        },
        "2017-04-28": {
            "1. open": "10.8200",
            "2. high": "11.0500",
            "3. low": "10.6700",
            "4. close": "11.0000",
            "5. adjusted close": "10.7127",
            "6. volume": "51263",
            "7. dividend amount": "0.0000",
            "8. split coefficient": "1.0000"
        },
        "2017-04-27": {
            "1. open": "11.0100",
            "2. high": "11.0470",
            "3. low": "10.7100",
            "4. close": "10.8200",
            "5. adjusted close": "10.5374",
            "6. volume": "58740",
            "7. dividend amount": "0.0000",
            "8. split coefficient": "1.0000"
        },
        "2017-04-26": {
            "1. open": "10.9400",
            "2. high": "11.1800",
            "3. low": "10.7000",
            "4. close": "10.9800",
            "5. adjusted close": "10.6932",
            "6. volume": "185630",
            "7. dividend amount": "0.0000",
            "8. split coefficient": "1.0000"
        },
        "2017-04-25": {
            "1. open": "11.0000",
            "2. high": "11.3000",
            "3. low": "10.8900",
            "4. close": "10.9900",
            "5. adjusted close": "10.7029",
            "6. volume": "128888",
            "7. dividend amount": "0.0000",
            "8. split coefficient": "1.0000"
        },
        "2017-04-24": {
            "1. open": "11.0400",
            "2. high": "11.2200",
            "3. low": "10.9500",
            "4. close": "11.0000",
            "5. adjusted close": "10.7127",
            "6. volume": "62429",
            "7. dividend amount": "0.0000",
            "8. split coefficient": "1.0000"
        },
        "2017-04-21": {
            "1. open": "11.2000",
            "2. high": "11.4600",
            "3. low": "10.9620",
            "4. close": "11.0700",
            "5. adjusted close": "10.7808",
            "6. volume": "88536",
            "7. dividend amount": "0.0000",
            "8. split coefficient": "1.0000"
        },
        "2017-04-20": {
            "1. open": "10.5000",
            "2. high": "11.2800",
            "3. low": "10.5000",
            "4. close": "11.2400",
            "5. adjusted close": "10.9464",
            "6. volume": "162654",
            "7. dividend amount": "0.0000",
            "8. split coefficient": "1.0000"
        },
        "2017-04-19": {
            "1. open": "11.0800",
            "2. high": "11.2000",
            "3. low": "10.8300",
            "4. close": "10.9600",
            "5. adjusted close": "10.6737",
            "6. volume": "245577",
            "7. dividend amount": "0.0000",
            "8. split coefficient": "1.0000"
        },
        "2017-04-18": {
            "1. open": "11.2750",
            "2. high": "11.3500",
            "3. low": "11.2000",
            "4. close": "11.2900",
            "5. adjusted close": "10.9951",
            "6. volume": "122276",
            "7. dividend amount": "0.0000",
            "8. split coefficient": "1.0000"
        },
        "2017-04-17": {
            "1. open": "11.1700",
            "2. high": "11.3200",
            "3. low": "11.1000",
            "4. close": "11.3000",
            "5. adjusted close": "11.0048",
            "6. volume": "88013",
            "7. dividend amount": "0.0000",
            "8. split coefficient": "1.0000"
        },
        "2017-04-13": {
            "1. open": "11.4000",
            "2. high": "11.4000",
            "3. low": "10.9000",
            "4. close": "11.1400",
            "5. adjusted close": "10.8490",
            "6. volume": "223744",
            "7. dividend amount": "0.0000",
            "8. split coefficient": "1.0000"
        },
        "2017-04-12": {
            "1. open": "11.7500",
            "2. high": "11.8000",
            "3. low": "11.1600",
            "4. close": "11.3100",
            "5. adjusted close": "11.0146",
            "6. volume": "167875",
            "7. dividend amount": "0.0000",
            "8. split coefficient": "1.0000"
        },
        "2017-04-11": {
            "1. open": "12.3800",
            "2. high": "12.3800",
            "3. low": "11.5000",
            "4. close": "11.8100",
            "5. adjusted close": "11.5015",
            "6. volume": "147810",
            "7. dividend amount": "0.0000",
            "8. split coefficient": "1.0000"
        },
        "2017-04-10": {
            "1. open": "12.6100",
            "2. high": "12.7500",
            "3. low": "12.2500",
            "4. close": "12.2800",
            "5. adjusted close": "11.9592",
            "6. volume": "89359",
            "7. dividend amount": "0.0000",
            "8. split coefficient": "1.0000"
        },
        "2017-04-07": {
            "1. open": "12.8000",
            "2. high": "12.9000",
            "3. low": "12.7000",
            "4. close": "12.7000",
            "5. adjusted close": "12.3682",
            "6. volume": "51765",
            "7. dividend amount": "0.0000",
            "8. split coefficient": "1.0000"
        },
        "2017-04-06": {
            "1. open": "12.7000",
            "2. high": "12.9300",
            "3. low": "12.7000",
            "4. close": "12.7900",
            "5. adjusted close": "12.4559",
            "6. volume": "37409",
            "7. dividend amount": "0.0850",
            "8. split coefficient": "1.0000"
        },
        "2017-04-05": {
            "1. open": "13.2700",
            "2. high": "13.2700",
            "3. low": "12.8700",
            "4. close": "12.9000",
            "5. adjusted close": "12.4801",
            "6. volume": "104768",
            "7. dividend amount": "0.0000",
            "8. split coefficient": "1.0000"
        },
        "2017-04-04": {
            "1. open": "13.2500",
            "2. high": "13.3700",
            "3. low": "13.2200",
            "4. close": "13.3700",
            "5. adjusted close": "12.9348",
            "6. volume": "44669",
            "7. dividend amount": "0.0000",
            "8. split coefficient": "1.0000"
        },
        "2017-04-03": {
            "1. open": "12.9700",
            "2. high": "13.2500",
            "3. low": "12.9140",
            "4. close": "13.2500",
            "5. adjusted close": "12.8187",
            "6. volume": "60135",
            "7. dividend amount": "0.0000",
            "8. split coefficient": "1.0000"
        },
        "2017-03-31": {
            "1. open": "13.4100",
            "2. high": "13.4100",
            "3. low": "12.7500",
            "4. close": "12.8200",
            "5. adjusted close": "12.4027",
            "6. volume": "515091",
            "7. dividend amount": "0.0000",
            "8. split coefficient": "1.0000"
        },
        "2017-03-30": {
            "1. open": "13.3100",
            "2. high": "13.5300",
            "3. low": "13.3000",
            "4. close": "13.4100",
            "5. adjusted close": "12.9735",
            "6. volume": "80394",
            "7. dividend amount": "0.0000",
            "8. split coefficient": "1.0000"
        },
        "2017-03-29": {
            "1. open": "13.4500",
            "2. high": "13.4900",
            "3. low": "13.3500",
            "4. close": "13.4000",
            "5. adjusted close": "12.9638",
            "6. volume": "42292",
            "7. dividend amount": "0.0000",
            "8. split coefficient": "1.0000"
        },
        "2017-03-28": {
            "1. open": "13.4800",
            "2. high": "13.5500",
            "3. low": "13.3700",
            "4. close": "13.3900",
            "5. adjusted close": "12.9541",
            "6. volume": "43060",
            "7. dividend amount": "0.0000",
            "8. split coefficient": "1.0000"
        },
        "2017-03-27": {
            "1. open": "13.3000",
            "2. high": "13.5550",
            "3. low": "13.3000",
            "4. close": "13.5100",
            "5. adjusted close": "13.0702",
            "6. volume": "40624",
            "7. dividend amount": "0.0000",
            "8. split coefficient": "1.0000"
        },
        "2017-03-24": {
            "1. open": "13.5500",
            "2. high": "13.5500",
            "3. low": "13.4000",
            "4. close": "13.5000",
            "5. adjusted close": "13.0606",
            "6. volume": "27449",
            "7. dividend amount": "0.0000",
            "8. split coefficient": "1.0000"
        },
        "2017-03-23": {
            "1. open": "13.5500",
            "2. high": "13.5500",
            "3. low": "13.4250",
            "4. close": "13.5100",
            "5. adjusted close": "13.0702",
            "6. volume": "31564",
            "7. dividend amount": "0.0000",
            "8. split coefficient": "1.0000"
        },
        "2017-03-22": {
            "1. open": "13.4000",
            "2. high": "13.5500",
            "3. low": "13.3660",
            "4. close": "13.5000",
            "5. adjusted close": "13.0606",
            "6. volume": "27466",
            "7. dividend amount": "0.0000",
            "8. split coefficient": "1.0000"
        },
        "2017-03-21": {
            "1. open": "13.4500",
            "2. high": "13.5000",
            "3. low": "13.3500",
            "4. close": "13.4000",
            "5. adjusted close": "12.9638",
            "6. volume": "59561",
            "7. dividend amount": "0.0000",
            "8. split coefficient": "1.0000"
        },
        "2017-03-20": {
            "1. open": "13.3300",
            "2. high": "13.5000",
            "3. low": "13.3100",
            "4. close": "13.5000",
            "5. adjusted close": "13.0606",
            "6. volume": "69939",
            "7. dividend amount": "0.0000",
            "8. split coefficient": "1.0000"
        },
        "2017-03-17": {
            "1. open": "13.7800",
            "2. high": "13.9200",
            "3. low": "13.2500",
            "4. close": "13.2500",
            "5. adjusted close": "12.8187",
            "6. volume": "220177",
            "7. dividend amount": "0.0000",
            "8. split coefficient": "1.0000"
        },
        "2017-03-16": {
            "1. open": "13.5000",
            "2. high": "13.9100",
            "3. low": "13.4800",
            "4. close": "13.9100",
            "5. adjusted close": "13.4572",
            "6. volume": "58102",
            "7. dividend amount": "0.0000",
            "8. split coefficient": "1.0000"
        },
        "2017-03-15": {
            "1. open": "13.5500",
            "2. high": "13.5580",
            "3. low": "13.4000",
            "4. close": "13.5200",
            "5. adjusted close": "13.0799",
            "6. volume": "28036",
            "7. dividend amount": "0.0000",
            "8. split coefficient": "1.0000"
        },
        "2017-03-14": {
            "1. open": "13.5300",
            "2. high": "13.5800",
            "3. low": "13.4100",
            "4. close": "13.5800",
            "5. adjusted close": "13.1379",
            "6. volume": "23034",
            "7. dividend amount": "0.0000",
            "8. split coefficient": "1.0000"
        },
        "2017-03-13": {
            "1. open": "13.5100",
            "2. high": "13.6000",
            "3. low": "13.4900",
            "4. close": "13.5700",
            "5. adjusted close": "13.1283",
            "6. volume": "56881",
            "7. dividend amount": "0.0000",
            "8. split coefficient": "1.0000"
        },
        "2017-03-10": {
            "1. open": "13.3500",
            "2. high": "13.5500",
            "3. low": "13.3500",
            "4. close": "13.5500",
            "5. adjusted close": "13.1089",
            "6. volume": "20099",
            "7. dividend amount": "0.0000",
            "8. split coefficient": "1.0000"
        },
        "2017-03-09": {
            "1. open": "13.4500",
            "2. high": "13.4500",
            "3. low": "13.3000",
            "4. close": "13.3000",
            "5. adjusted close": "12.8671",
            "6. volume": "86014",
            "7. dividend amount": "0.0000",
            "8. split coefficient": "1.0000"
        },
        "2017-03-08": {
            "1. open": "13.5000",
            "2. high": "13.5350",
            "3. low": "13.4000",
            "4. close": "13.4100",
            "5. adjusted close": "12.9735",
            "6. volume": "91019",
            "7. dividend amount": "0.0000",
            "8. split coefficient": "1.0000"
        },
        "2017-03-07": {
            "1. open": "13.5100",
            "2. high": "13.6600",
            "3. low": "13.5000",
            "4. close": "13.5000",
            "5. adjusted close": "13.0606",
            "6. volume": "70181",
            "7. dividend amount": "0.0000",
            "8. split coefficient": "1.0000"
        },
        "2017-03-06": {
            "1. open": "13.5100",
            "2. high": "13.6000",
            "3. low": "13.5100",
            "4. close": "13.5200",
            "5. adjusted close": "13.0799",
            "6. volume": "28546",
            "7. dividend amount": "0.0000",
            "8. split coefficient": "1.0000"
        },
        "2017-03-03": {
            "1. open": "13.5800",
            "2. high": "13.6000",
            "3. low": "13.5100",
            "4. close": "13.5100",
            "5. adjusted close": "13.0702",
            "6. volume": "28038",
            "7. dividend amount": "0.0000",
            "8. split coefficient": "1.0000"
        },
        "2017-03-02": {
            "1. open": "13.6900",
            "2. high": "13.7400",
            "3. low": "13.5000",
            "4. close": "13.5100",
            "5. adjusted close": "13.0702",
            "6. volume": "51773",
            "7. dividend amount": "0.0000",
            "8. split coefficient": "1.0000"
        },
        "2017-03-01": {
            "1. open": "13.6300",
            "2. high": "13.7500",
            "3. low": "13.5100",
            "4. close": "13.7200",
            "5. adjusted close": "13.2734",
            "6. volume": "256494",
            "7. dividend amount": "0.0000",
            "8. split coefficient": "1.0000"
        },
        "2017-02-28": {
            "1. open": "13.9900",
            "2. high": "14.0900",
            "3. low": "13.5000",
            "4. close": "13.6000",
            "5. adjusted close": "13.1573",
            "6. volume": "124673",
            "7. dividend amount": "0.0000",
            "8. split coefficient": "1.0000"
        },
        "2017-02-27": {
            "1. open": "14.0500",
            "2. high": "14.0820",
            "3. low": "13.8500",
            "4. close": "14.0200",
            "5. adjusted close": "13.5636",
            "6. volume": "55805",
            "7. dividend amount": "0.0000",
            "8. split coefficient": "1.0000"
        },
        "2017-02-24": {
            "1. open": "13.8400",
            "2. high": "14.2400",
            "3. low": "13.7700",
            "4. close": "14.0400",
            "5. adjusted close": "13.5830",
            "6. volume": "44623",
            "7. dividend amount": "0.0000",
            "8. split coefficient": "1.0000"
        },
        "2017-02-23": {
            "1. open": "13.8300",
            "2. high": "13.9800",
            "3. low": "13.6000",
            "4. close": "13.9500",
            "5. adjusted close": "13.4959",
            "6. volume": "51244",
            "7. dividend amount": "0.0000",
            "8. split coefficient": "1.0000"
        },
        "2017-02-22": {
            "1. open": "13.5500",
            "2. high": "13.7800",
            "3. low": "13.5200",
            "4. close": "13.6500",
            "5. adjusted close": "13.2057",
            "6. volume": "14902",
            "7. dividend amount": "0.0000",
            "8. split coefficient": "1.0000"
        },
        "2017-02-21": {
            "1. open": "13.4300",
            "2. high": "13.5800",
            "3. low": "13.3700",
            "4. close": "13.5400",
            "5. adjusted close": "13.0992",
            "6. volume": "23669",
            "7. dividend amount": "0.0000",
            "8. split coefficient": "1.0000"
        },
        "2017-02-17": {
            "1. open": "13.5000",
            "2. high": "13.5500",
            "3. low": "13.5000",
            "4. close": "13.5100",
            "5. adjusted close": "13.0702",
            "6. volume": "22384",
            "7. dividend amount": "0.0000",
            "8. split coefficient": "1.0000"
        },
        "2017-02-16": {
            "1. open": "13.5500",
            "2. high": "13.5500",
            "3. low": "13.5000",
            "4. close": "13.5000",
            "5. adjusted close": "13.0606",
            "6. volume": "105247",
            "7. dividend amount": "0.0000",
            "8. split coefficient": "1.0000"
        },
        "2017-02-15": {
            "1. open": "13.6400",
            "2. high": "13.7600",
            "3. low": "13.5700",
            "4. close": "13.5800",
            "5. adjusted close": "13.1379",
            "6. volume": "60020",
            "7. dividend amount": "0.0000",
            "8. split coefficient": "1.0000"
        },
        "2017-02-14": {
            "1. open": "13.5200",
            "2. high": "13.6000",
            "3. low": "13.2700",
            "4. close": "13.5100",
            "5. adjusted close": "13.0702",
            "6. volume": "209223",
            "7. dividend amount": "0.0000",
            "8. split coefficient": "1.0000"
        },
        "2017-02-13": {
            "1. open": "13.5000",
            "2. high": "13.7400",
            "3. low": "13.5000",
            "4. close": "13.5000",
            "5. adjusted close": "13.0606",
            "6. volume": "176622",
            "7. dividend amount": "0.0000",
            "8. split coefficient": "1.0000"
        },
        "2017-02-10": {
            "1. open": "15.0000",
            "2. high": "15.0000",
            "3. low": "13.5000",
            "4. close": "13.5000",
            "5. adjusted close": "13.0606",
            "6. volume": "1125393",
            "7. dividend amount": "0.0000",
            "8. split coefficient": "1.0000"
        }
    }
}